Workbook
Name Capex___of_sales: 'Forecast + Valuation'!$C$19:$D$19
Name Change_in_net_working_capital____of_incremental_sales: 'Forecast + Valuation'!$C$20:$D$20
Name D_A___of_sales: 'Forecast + Valuation'!$C$18:$D$18
Name Effective_tax_rate: 'Forecast + Valuation'!$C$17:$D$17
Name Operating_margin: 'Forecast + Valuation'!$C$16:$D$16
Name Revenue_growth_rate: 'Forecast + Valuation'!$C$15:$D$15
Name Terminal__perpetuity__growth_rate: 'Forecast + Valuation'!$C$21:$D$21
Name WACC: 'Forecast + Valuation'!$D$45
Name WACC__discount_rate: 'Forecast + Valuation'!#REF!

Sheet Intro
B2: Dollarama Inc.
B3: Company Financial Analysis + Valuation
B4: By Asley Lopez Robleto
B6: What's included:
B7: Common Analysis
B8: Ratio analysis
B9: Cash Flow quality analysis
B10: Forecast + Valuation
B12: FY2021-FY2026
B13: Financial position
B14: Income statement
B15: Cash flow statement

Sheet Common Analysis
B2: Dollarama Inc.
B3: Common-Size Statements (Vertical Analysis)
B4: Income statement items as % of Sales <=> Balance sheet items as % of Total assets
B6: (% of Sales / % of Total assets) | D6: FY2021 | E6: FY2022 | F6: FY2023 | G6: FY2024 | H6: FY2025 | I6: FY2026
B7: Income statement - % of Sales
B8: Cost of sales | D8: ='Income Statement'!D8/'Income Statement'!D$7 -> 0.56162507 | E8: ='Income Statement'!E8/'Income Statement'!E$7 -> 0.56076426 | F8: ='Income Statement'!F8/'Income Statement'!F$7 -> 0.56494782 | G8: ='Income Statement'!G8/'Income Statement'!G$7 -> 0.55457883 | H8: ='Income Statement'!H8/'Income Statement'!H$7 -> 0.54877895 | I8: ='Income Statement'!I8/'Income Statement'!I$7 -> 0.54950719
B9: Gross profit | D9: ='Income Statement'!D9/'Income Statement'!D$7 -> 0.43837493 | E9: ='Income Statement'!E9/'Income Statement'!E$7 -> 0.43923574 | F9: ='Income Statement'!F9/'Income Statement'!F$7 -> 0.43505218 | G9: ='Income Statement'!G9/'Income Statement'!G$7 -> 0.44542117 | H9: ='Income Statement'!H9/'Income Statement'!H$7 -> 0.45122105 | I9: ='Income Statement'!I9/'Income Statement'!I$7 -> 0.45049281
B10: G&A and store operating expenses | D10: ='Income Statement'!D10/'Income Statement'!D$7 -> 0.16244161 | E10: ='Income Statement'!E10/'Income Statement'!E$7 -> 0.15074302 | F10: ='Income Statement'!F10/'Income Statement'!F$7 -> 0.14255866 | G10: ='Income Statement'!G10/'Income Statement'!G$7 -> 0.14399538 | H10: ='Income Statement'!H10/'Income Statement'!H$7 -> 0.14504085 | I10: ='Income Statement'!I10/'Income Statement'!I$7 -> 0.1506789
B11: Depreciation and amortization | D11: ='Income Statement'!D11/'Income Statement'!D$7 -> 0.066968618 | E11: ='Income Statement'!E11/'Income Statement'!E$7 -> 0.068800841 | F11: ='Income Statement'!F11/'Income Statement'!F$7 -> 0.065665745 | G11: ='Income Statement'!G11/'Income Statement'!G$7 -> 0.059335495 | H11: ='Income Statement'!H11/'Income Statement'!H$7 -> 0.059690682 | I11: ='Income Statement'!I11/'Income Statement'!I$7 -> 0.059132793
B12: Operating income | D12: ='Income Statement'!D13/'Income Statement'!D$7 -> 0.21384615 | E12: ='Income Statement'!E13/'Income Statement'!E$7 -> 0.22735427 | F12: ='Income Statement'!F13/'Income Statement'!F$7 -> 0.2358128 | G12: ='Income Statement'!G13/'Income Statement'!G$7 -> 0.25492284 | H12: ='Income Statement'!H13/'Income Statement'!H$7 -> 0.26674557 | I12: ='Income Statement'!I13/'Income Statement'!I$7 -> 0.26707893
B13: Net financing costs | D13: ='Income Statement'!D15/'Income Statement'!D$7 -> 0.023755551 | E13: ='Income Statement'!E15/'Income Statement'!E$7 -> 0.021062349 | F13: ='Income Statement'!F15/'Income Statement'!F$7 -> 0.022837901 | G13: ='Income Statement'!G15/'Income Statement'!G$7 -> 0.02468611 | H13: ='Income Statement'!H15/'Income Statement'!H$7 -> 0.025538484 | I13: ='Income Statement'!I15/'Income Statement'!I$7 -> 0.02536194
B14: Earnings before income taxes | D14: ='Income Statement'!D16/'Income Statement'!D$7 -> 0.1900906 | E14: ='Income Statement'!E16/'Income Statement'!E$7 -> 0.20629192 | F14: ='Income Statement'!F16/'Income Statement'!F$7 -> 0.2129749 | G14: ='Income Statement'!G16/'Income Statement'!G$7 -> 0.23023673 | H14: ='Income Statement'!H16/'Income Statement'!H$7 -> 0.24120708 | I14: ='Income Statement'!I16/'Income Statement'!I$7 -> 0.24314317
B15: Income taxes | D15: ='Income Statement'!D17/'Income Statement'!D$7 -> 0.049923763 | E15: ='Income Statement'!E17/'Income Statement'!E$7 -> 0.053162019 | F15: ='Income Statement'!F17/'Income Statement'!F$7 -> 0.054276283 | G15: ='Income Statement'!G17/'Income Statement'!G$7 -> 0.058019228 | H15: ='Income Statement'!H17/'Income Statement'!H$7 -> 0.058996171 | I15: ='Income Statement'!I17/'Income Statement'!I$7 -> 0.062674258
B16: Net earnings | D16: ='Income Statement'!D18/'Income Statement'!D$7 -> 0.14016684 | E16: ='Income Statement'!E18/'Income Statement'!E$7 -> 0.1531299 | F16: ='Income Statement'!F18/'Income Statement'!F$7 -> 0.15869862 | G16: ='Income Statement'!G18/'Income Statement'!G$7 -> 0.1722175 | H16: ='Income Statement'!H18/'Income Statement'!H$7 -> 0.18221091 | I16: ='Income Statement'!I18/'Income Statement'!I$7 -> 0.18046891
B18: Balance sheet - % of Total assets
B19: Cash and cash equivalents | D19: ='Financial Position'!D9/'Financial Position'!D$27 -> 0.10397027 | E19: ='Financial Position'!E9/'Financial Position'!E$27 -> 0.017486629 | F19: ='Financial Position'!F9/'Financial Position'!F$27 -> 0.021010006 | G19: ='Financial Position'!G9/'Financial Position'!G$27 -> 0.059638761 | H19: ='Financial Position'!H9/'Financial Position'!H$27 -> 0.0189253 | I19: ='Financial Position'!I9/'Financial Position'!I$27 -> 0.043867896
B20: Inventories | D20: ='Financial Position'!D14/'Financial Position'!D$27 -> 0.14931177 | E20: ='Financial Position'!E14/'Financial Position'!E$27 -> 0.14542094 | F20: ='Financial Position'!F14/'Financial Position'!F$27 -> 0.19859758 | G20: ='Financial Position'!G14/'Financial Position'!G$27 -> 0.17417942 | H20: ='Financial Position'!H14/'Financial Position'!H$27 -> 0.14208746 | I20: ='Financial Position'!I14/'Financial Position'!I$27 -> 0.14595444
B21: Total current assets | D21: ='Financial Position'!D16/'Financial Position'!D$27 -> 0.26051803 | E21: ='Financial Position'!E16/'Financial Position'!E$27 -> 0.1765365 | F21: ='Financial Position'!F16/'Financial Position'!F$27 -> 0.24004763 | G21: ='Financial Position'!G16/'Financial Position'!G$27 -> 0.24870645 | H21: ='Financial Position'!H16/'Financial Position'!H$27 -> 0.18530859 | I21: ='Financial Position'!I16/'Financial Position'!I$27 -> 0.20136519
B22: Right-of-use assets | D22: ='Financial Position'!D19/'Financial Position'!D$27 -> 0.31835224 | E22: ='Financial Position'!E19/'Financial Position'!E$27 -> 0.36427523 | F22: ='Financial Position'!F19/'Financial Position'!F$27 -> 0.35267144 | G22: ='Financial Position'!G19/'Financial Position'!G$27 -> 0.33979551 | H22: ='Financial Position'!H19/'Financial Position'!H$27 -> 0.32540148 | I22: ='Financial Position'!I19/'Financial Position'!I$27 -> 0.31716028
B23: Property, plant and equipment | D23: ='Financial Position'!D20/'Financial Position'!D$27 -> 0.16797151 | E23: ='Financial Position'!E20/'Financial Position'!E$27 -> 0.1874897 | F23: ='Financial Position'!F20/'Financial Position'!F$27 -> 0.16655753 | G23: ='Financial Position'!G20/'Financial Position'!G$27 -> 0.18067344 | H23: ='Financial Position'!H20/'Financial Position'!H$27 -> 0.16141537 | I23: ='Financial Position'!I20/'Financial Position'!I$27 -> 0.16650442
B24: Goodwill | D24: ='Financial Position'!D23/'Financial Position'!D$27 -> 0.17230724 | E24: ='Financial Position'!E23/'Financial Position'!E$27 -> 0.17909952 | F24: ='Financial Position'!F23/'Financial Position'!F$27 -> 0.15100289 | G24: ='Financial Position'!G23/'Financial Position'!G$27 -> 0.13826678 | H24: ='Financial Position'!H23/'Financial Position'!H$27 -> 0.11226713 | I24: ='Financial Position'!I23/'Financial Position'!I$27 -> 0.10606929
B25: Equity-accounted investments | D25: ='Financial Position'!D24/'Financial Position'!D$27 -> 0.042471541 | E25: ='Financial Position'!E24/'Financial Position'!E$27 -> 0.052152766 | F25: ='Financial Position'!F24/'Financial Position'!F$27 -> 0.055557492 | G25: ='Financial Position'!G24/'Financial Position'!G$27 -> 0.060671893 | H25: ='Financial Position'!H24/'Financial Position'!H$27 -> 0.17456752 | I25: ='Financial Position'!I24/'Financial Position'!I$27 -> 0.1700245
B26: Total assets | D26: ='Financial Position'!D27/'Financial Position'!D$27 -> 1 | E26: ='Financial Position'!E27/'Financial Position'!E$27 -> 1 | F26: ='Financial Position'!F27/'Financial Position'!F$27 -> 1 | G26: ='Financial Position'!G27/'Financial Position'!G$27 -> 1 | H26: ='Financial Position'!H27/'Financial Position'!H$27 -> 1 | I26: ='Financial Position'!I27/'Financial Position'!I$27 -> 1
B27: Total current liabilities | D27: ='Financial Position'!D38/'Financial Position'!D$27 -> 0.31279461 | E27: ='Financial Position'!E38/'Financial Position'!E$27 -> 0.22440681 | F27: ='Financial Position'!F38/'Financial Position'!F$27 -> 0.24127739 | G27: ='Financial Position'!G38/'Financial Position'!G$27 -> 0.12877975 | H27: ='Financial Position'!H38/'Financial Position'!H$27 -> 0.15646612 | I27: ='Financial Position'!I38/'Financial Position'!I$27 -> 0.17836944
B28: Non-current portion of long-term debt | D28: ='Financial Position'!D42/'Financial Position'!D$27 -> 0.24719266 | E28: ='Financial Position'!E42/'Financial Position'!E$27 -> 0.37879082 | F28: ='Financial Position'!F42/'Financial Position'!F$27 -> 0.3613511 | G28: ='Financial Position'!G42/'Financial Position'!G$27 -> 0.4261211 | H28: ='Financial Position'!H42/'Financial Position'!H$27 -> 0.30989271 | I28: ='Financial Position'!I42/'Financial Position'!I$27 -> 0.29462057
B29: Non-current portion of lease liabilities | D29: ='Financial Position'!D43 / 'Financial Position'!D$27 -> 0.33187815 | E29: ='Financial Position'!E43 / 'Financial Position'!E$27 -> 0.37567139 | F29: ='Financial Position'!F43 / 'Financial Position'!F$27 -> 0.3614233 | G29: ='Financial Position'!G43 / 'Financial Position'!G$27 -> 0.3485644 | H29: ='Financial Position'!H43 / 'Financial Position'!H$27 -> 0.3313909 | I29: ='Financial Position'!I43 / 'Financial Position'!I$27 -> 0.31656769
B30: Total liabilities | D30: ='Financial Position'!D45/'Financial Position'!D27 -> 0.92072109 | E30: ='Financial Position'!E45/'Financial Position'!E27 -> 1.0162503 | F30: ='Financial Position'!F45/'Financial Position'!F27 -> 0.99410539 | G30: ='Financial Position'!G45/'Financial Position'!G27 -> 0.92764505 | H30: ='Financial Position'!H45/'Financial Position'!H27 -> 0.81670017 | I30: ='Financial Position'!I45/'Financial Position'!I27 -> 0.80738023
B31: Total shareholders' equity | D31: ='Financial Position'!D53/'Financial Position'!D$27 -> 0.079278915 | E31: ='Financial Position'!E53/'Financial Position'!E$27 -> -0.016250275 | F31: ='Financial Position'!F53/'Financial Position'!F$27 -> 0.0058946116 | G31: ='Financial Position'!G53/'Financial Position'!G$27 -> 0.072354946 | H31: ='Financial Position'!H53/'Financial Position'!H$27 -> 0.18329983 | I31: ='Financial Position'!I53/'Financial Position'!I$27 -> 0.19261977

Sheet Ratio
B2: Dollarama Inc.
B3: Ratio Analysis
B4: All ratios use fiscal year-end (not average) balance sheet figures for consistency across all 6 years
B6: (CAD $ thousands) | D6: FY2021 | E6: FY2022 | F6: FY2023 | G6: FY2024 | H6: FY2025 | I6: FY2026
B7: Liquidity
B8: Current ratio (Current assets / Current liabilities) | D8: ='Financial Position'!D16/'Financial Position'!D38 -> 0.8328725 | E8: ='Financial Position'!E16/'Financial Position'!E38 -> 0.78668064 | F8: ='Financial Position'!F16/'Financial Position'!F38 -> 0.99490315 | G8: ='Financial Position'!G16/'Financial Position'!G38 -> 1.9312543 | H8: ='Financial Position'!H16/'Financial Position'!H38 -> 1.1843369 | I8: ='Financial Position'!I16/'Financial Position'!I38 -> 1.128922
B9: Quick ratio ((Current assets − Inventory − Prepaid) / Current liabilities) | D9: =('Financial Position'!D16-'Financial Position'!D14-'Financial Position'!D13)/'Financial Position'!D16 -> 0.41818783 | E9: =('Financial Position'!E16-'Financial Position'!E14-'Financial Position'!E13)/'Financial Position'!E16 -> 0.15794565 | F9: =('Financial Position'!F16-'Financial Position'!F14-'Financial Position'!F13)/'Financial Position'!F16 -> 0.15239505 | G9: =('Financial Position'!G16-'Financial Position'!G14-'Financial Position'!G13)/'Financial Position'!G16 -> 0.2892178 | H9: =('Financial Position'!H16-'Financial Position'!H14-'Financial Position'!H13)/'Financial Position'!H16 -> 0.22165856 | I9: =('Financial Position'!I16-'Financial Position'!I14-'Financial Position'!I13)/'Financial Position'!I16 -> 0.24991114
B10: Working capital ($ thousands) | D10: ='Financial Position'!D16-'Financial Position'!D38 -> -220803 | E10: ='Financial Position'!E16-'Financial Position'!E38 -> -194524 | F10: ='Financial Position'!F16-'Financial Position'!F38 -> -5927 | G10: ='Financial Position'!G16-'Financial Position'!G38 -> 631247 | H10: ='Financial Position'!H16-'Financial Position'!H38 -> 186974 | I10: ='Financial Position'!I16-'Financial Position'!I38 -> 173810
B12: Profitability
B13: Gross margin | D13: ='Income Statement'!D9/'Income Statement'!D7 -> 0.43837493 | E13: ='Income Statement'!E9/'Income Statement'!E7 -> 0.43923574 | F13: ='Income Statement'!F9/'Income Statement'!F7 -> 0.43505218 | G13: ='Income Statement'!G9/'Income Statement'!G7 -> 0.44542117 | H13: ='Income Statement'!H9/'Income Statement'!H7 -> 0.45122105 | I13: ='Income Statement'!I9/'Income Statement'!I7 -> 0.45049281
B14: Operating margin | D14: ='Income Statement'!D13/'Income Statement'!D7 -> 0.21384615 | E14: ='Income Statement'!E13/'Income Statement'!E7 -> 0.22735427 | F14: ='Income Statement'!F13/'Income Statement'!F7 -> 0.2358128 | G14: ='Income Statement'!G13/'Income Statement'!G7 -> 0.25492284 | H14: ='Income Statement'!H13/'Income Statement'!H7 -> 0.26674557 | I14: ='Income Statement'!I13/'Income Statement'!I7 -> 0.26707893
B15: Net margin | D15: ='Income Statement'!D18/'Income Statement'!D7 -> 0.14016684 | E15: ='Income Statement'!E18/'Income Statement'!E7 -> 0.1531299 | F15: ='Income Statement'!F18/'Income Statement'!F7 -> 0.15869862 | G15: ='Income Statement'!G18/'Income Statement'!G7 -> 0.1722175 | H15: ='Income Statement'!H18/'Income Statement'!H7 -> 0.18221091 | I15: ='Income Statement'!I18/'Income Statement'!I7 -> 0.18046891
B16: Return on assets (Net earnings / Total assets, year-end) | D16: ='Income Statement'!D18/'Financial Position'!D27 -> 0.13361315 | E16: ='Income Statement'!E18/'Financial Position'!E27 -> 0.16319894 | F16: ='Income Statement'!F18/'Financial Position'!F27 -> 0.16637349 | G16: ='Income Statement'!G18/'Financial Position'!G27 -> 0.19197102 | H16: ='Income Statement'!H18/'Financial Position'!H27 -> 0.18025891 | I16: ='Income Statement'!I18/'Financial Position'!I27 -> 0.17324385
B17: Return on equity (Net earnings / Total equity, year-end) | D17: ='Income Statement'!D18/'Financial Position'!D53 -> 1.6853554 | E17: ='Income Statement'!E18/'Financial Position'!E53 -> -10.042842 | F17: ='Income Statement'!F18/'Financial Position'!F53 -> 28.224674 | G17: ='Income Statement'!G18/'Financial Position'!G53 -> 2.6531845 | H17: ='Income Statement'!H18/'Financial Position'!H53 -> 0.98341017 | I17: ='Income Statement'!I18/'Financial Position'!I53 -> 0.89940847
B19: Efficiency
B20: Inventory turnover (COGS / Inventory, year-end) | D20: ='Income Statement'!D8/'Financial Position'!D14 -> 3.5855547 | E20: ='Income Statement'!E8/'Financial Position'!E14 -> 4.1097056 | F20: ='Income Statement'!F8/'Financial Position'!F14 -> 2.9822592 | G20: ='Income Statement'!G8/'Financial Position'!G14 -> 3.549154 | H20: ='Income Statement'!H8/'Financial Position'!H14 -> 3.820886 | I20: ='Income Statement'!I8/'Financial Position'!I14 -> 3.6141945
B21: Days inventory outstanding (365 / Inventory turnover) | D21: =365/D20 -> 101.79736 | E21: =365/E20 -> 88.814148 | F21: =365/F20 -> 122.39043 | G21: =365/G20 -> 102.84141 | H21: =365/H20 -> 95.527582 | I21: =365/I20 -> 100.99069
B22: Days payable outstanding (AP / COGS × 365) | D22: ='Financial Position'!D31/'Income Statement'!D8*365 -> 40.84969 | E22: ='Financial Position'!E31/'Income Statement'!E8*365 -> 42.552643 | F22: ='Financial Position'!F31/'Income Statement'!F8*365 -> 43.073436 | G22: ='Financial Position'!G31/'Income Statement'!G8*365 -> 37.505775 | H22: ='Financial Position'!H31/'Income Statement'!H8*365 -> 36.806995 | I22: ='Financial Position'!I31/'Income Statement'!I8*365 -> 42.272593
B23: Days sales outstanding (AR / Sales × 365) | D23: ='Financial Position'!D10/'Income Statement'!D8*365 -> 3.3164385 | E23: ='Financial Position'!E10/'Income Statement'!E8*365 -> 3.9467811 | F23: ='Financial Position'!F10/'Income Statement'!F8*365 -> 7.1976171 | G23: ='Financial Position'!G10/'Income Statement'!G8*365 -> 3.6427009 | H23: ='Financial Position'!H10/'Income Statement'!H8*365 -> 4.8368685 | I23: ='Financial Position'!I10/'Income Statement'!I8*365 -> 3.5245012
B24: Asset turnover (Sales / Total assets, year-end) | D24: ='Income Statement'!D7/'Financial Position'!D27 -> 0.95324364 | E24: ='Income Statement'!E7/'Financial Position'!E27 -> 1.0657549 | F24: ='Income Statement'!F7/'Financial Position'!F27 -> 1.0483613 | G24: ='Income Statement'!G7/'Financial Position'!G27 -> 1.114701 | H24: ='Income Statement'!H7/'Financial Position'!H27 -> 0.98928716 | I24: ='Income Statement'!I7/'Financial Position'!I27 -> 0.95996508
B26: Leverage
B27: Total liabilities / Total equity | D27: ='Financial Position'!D45/'Financial Position'!D53 -> 11.613694 | E27: ='Financial Position'!E45/'Financial Position'!E53 -> -62.53742 | F27: ='Financial Position'!F45/'Financial Position'!F53 -> 168.64646 | G27: ='Financial Position'!G45/'Financial Position'!G53 -> 12.820755 | H27: ='Financial Position'!H45/'Financial Position'!H53 -> 4.4555425 | I27: ='Financial Position'!I45/'Financial Position'!I53 -> 4.1915752
B28: Total liabilities / Total assets | D28: ='Financial Position'!D45/'Financial Position'!D27 -> 0.92072109 | E28: ='Financial Position'!E45/'Financial Position'!E27 -> 1.0162503 | F28: ='Financial Position'!F45/'Financial Position'!F27 -> 0.99410539 | G28: ='Financial Position'!G45/'Financial Position'!G27 -> 0.92764505 | H28: ='Financial Position'!H45/'Financial Position'!H27 -> 0.81670017 | I28: ='Financial Position'!I45/'Financial Position'!I27 -> 0.80738023
B29: EBITDA (Operating income + D&A, per income statement) | D29: ='Income Statement'!D13+'Income Statement'!D11 -> 1130633 | E29: ='Income Statement'!E13+'Income Statement'!E11 -> 1282577 | F29: ='Income Statement'!F13+'Income Statement'!F11 -> 1523293 | G29: ='Income Statement'!G13+'Income Statement'!G11 -> 1843863 | H29: ='Income Statement'!H13+'Income Statement'!H11 -> 2093483 | I29: ='Income Statement'!I13+'Income Statement'!I11 -> 2366912
B30: Interest-bearing debt (ST borrowings + current & non-current LT debt) | D30: ='Financial Position'!D32+'Financial Position'!D36+'Financial Position'!D42 -> 1876900 | E30: ='Financial Position'!E32+'Financial Position'!E36+'Financial Position'!E42 -> 1886300 | F30: ='Financial Position'!F32+'Financial Position'!F36+'Financial Position'!F42 -> 2251903 | G30: ='Financial Position'!G32+'Financial Position'!G36+'Financial Position'!G42 -> 2264394 | H30: ='Financial Position'!H32+'Financial Position'!H36+'Financial Position'!H42 -> 2282679 | I30: ='Financial Position'!I32+'Financial Position'!I36+'Financial Position'!I42 -> 2625121
B31: Net debt / EBITDA ((Interest-bearing debt − Cash) / EBITDA) | D31: =(D30-'Financial Position'!D9)/Ratio!D29 -> 1.2716381 | E31: =(E30-'Financial Position'!E9)/Ratio!E29 -> 1.4153084 | F31: =(F30-'Financial Position'!F9)/Ratio!F29 -> 1.4118374 | G31: =(G30-'Financial Position'!G9)/Ratio!G29 -> 1.0578221 | H31: =(H30-'Financial Position'!H9)/Ratio!H29 -> 1.0317705 | I31: =(I30-'Financial Position'!I9)/Ratio!I29 -> 0.96900603
B32: Interest coverage (Operating income / Net financing costs) | D32: ='Income Statement'!D13/'Income Statement'!D15 -> 9.0019447 | E32: ='Income Statement'!E13/'Income Statement'!E15 -> 10.794345 | F32: ='Income Statement'!F13/'Income Statement'!F15 -> 10.325502 | G32: ='Income Statement'!G13/'Income Statement'!G15 -> 10.32657 | H32: ='Income Statement'!H13/'Income Statement'!H15 -> 10.444847 | I32: ='Income Statement'!I13/'Income Statement'!I15 -> 10.530698

Sheet DuPont Analysis
B2: Dollarama Inc.
B3: DuPont ROE Decomposition
B4: ROE = Net margin × Asset turnover × Equity multiplier. Decomposes WHY ROE moved: pricing/cost control, asset efficiency, or leverage.
B5: Important note: FY2021-FY2024 are flagged: equity was thin or negative through sustained buybacks, so the equity multiplier and ROE are extreme and not very meaningful in those years. => read the trend into FY2025-FY2026 (when equity rebuilt), not the FY2021-FY2024 levels at face value.
B7: (CAD $ thousands) | D7: FY2021 | E7: FY2022 | F7: FY2023 | G7: FY2024 | H7: FY2025 | I7: FY2026
B8: Net margin (Net earnings / Sales) | D8: ='Income Statement'!D18/'Income Statement'!D7 -> 0.14016684 | E8: ='Income Statement'!E18/'Income Statement'!E7 -> 0.1531299 | F8: ='Income Statement'!F18/'Income Statement'!F7 -> 0.15869862 | G8: ='Income Statement'!G18/'Income Statement'!G7 -> 0.1722175 | H8: ='Income Statement'!H18/'Income Statement'!H7 -> 0.18221091 | I8: ='Income Statement'!I18/'Income Statement'!I7 -> 0.18046891
B9: Asset turnover (Sales / Total assets) | D9: ='Income Statement'!D7/'Financial Position'!D27 -> 0.95324364 | E9: ='Income Statement'!E7/'Financial Position'!E27 -> 1.0657549 | F9: ='Income Statement'!F7/'Financial Position'!F27 -> 1.0483613 | G9: ='Income Statement'!G7/'Financial Position'!G27 -> 1.114701 | H9: ='Income Statement'!H7/'Financial Position'!H27 -> 0.98928716 | I9: ='Income Statement'!I7/'Financial Position'!I27 -> 0.95996508
B10: Equity multiplier (Total assets / Total equity) | D10: ='Financial Position'!D27/'Financial Position'!D53 -> 12.613694 | E10: ='Financial Position'!E27/'Financial Position'!E53 -> -61.53742 | F10: ='Financial Position'!F27/'Financial Position'!F53 -> 169.64646 | G10: ='Financial Position'!G27/'Financial Position'!G53 -> 13.820755 | H10: ='Financial Position'!H27/'Financial Position'!H53 -> 5.4555425 | I10: ='Financial Position'!I27/'Financial Position'!I53 -> 5.1915752
B12: ROE (Net margin × Asset turnover × Equity multiplier) | D12: =D8*D9*D10 -> 1.6853554 | E12: =E8*E9*E10 -> -10.042842 | F12: =F8*F9*F10 -> 28.224674 | G12: =G8*G9*G10 -> 2.6531845 | H12: =H8*H9*H10 -> 0.98341017 | I12: =I8*I9*I10 -> 0.89940847
B13: ROE (Net earnings / Total equity, direct) | D13: ='Income Statement'!D18/'Financial Position'!D53 -> 1.6853554 | E13: ='Income Statement'!E18/'Financial Position'!E53 -> -10.042842 | F13: ='Income Statement'!F18/'Financial Position'!F53 -> 28.224674 | G13: ='Income Statement'!G18/'Financial Position'!G53 -> 2.6531845 | H13: ='Income Statement'!H18/'Financial Position'!H53 -> 0.98341017 | I13: ='Income Statement'!I18/'Financial Position'!I53 -> 0.89940847

Sheet MA Note
B2: Dollarama Inc.
B3: M&A Spotlight: The Reject Shop / Dollarama Australia Acquisition
B4: Closed July 21, 2025 (within FY2026, which ended Feb 1, 2026) => Dollarama acquired The Reject Shop Limited, an Australian discount retailer, now operating as Dollarama Australia Pty Limited. This is the first year the three core statements reflect a Canada + Australia segment structure.
B6: What the three core statements show directly
B8: (CAD $ thousands, unless noted) | D8: FY2025 | E8: FY2026
B9: Goodwill, prior year-end | D9: ='Financial Position'!H23 -> 727782
B10: Goodwill, current year-end | E10: ='Financial Position'!I23 -> 801709
B11: Implied change in goodwill | E11: =E10-D9 -> 73927
B13: Cash paid for acquisition, net of cash acquired (CF, investing) | E13: ='Cash Flow'!I29 -> -181831
B15: What we can and cannot conclude from IS / BS / CF alone
B17: Goodwill rose by the amount shown above between FY2025 and FY2026. That change is consistent with a purchase-price allocation from the acquisition, but goodwill can also move from FX translation of an existing foreign-currency goodwill balance. It's important to say we cannot separate the two effects from these three.
B19: The $181.8mm cash outflow for 'Acquisition of a business, net of cash acquired' is the actual purchase consideration paid in cash; it does not by itself tell us the fair value of assets acquired, liabilities assumed, or any non-controlling interest recognized. So, keep that in mind.
B21: FY2026's foreign currency translation adjustment on the income statement (-$70.2mm, the largest in the six-year window) is consistent with the business gaining a new AUD-denominated subsidiary that now needs retranslation each period.
B23: Equity-accounted investments also jumped materially in FY2025=>FY2026 (see Income Statement tab), but that looks driven by Dollarama's existing equity-method holdings (e.g., Dollarcity) rather than this acquisition, since the purchase is booked as a separate consolidated-subsidiary line, not through the equity-method investment balance.

Sheet CF Quality
B2: Dollarama Inc.
B3: Cash Flow Quality
B4: Tests whether reported earnings are backed by real cash generation, and how much cash is left over after reinvesting in the store network.
B6: (CAD $ thousands) | D6: FY2021 | E6: FY2022 | F6: FY2023 | G6: FY2024 | H6: FY2025 | I6: FY2026
B7: Net cash from operating activities (OCF) | D7: ='Cash Flow'!D26 -> 888622 | E7: ='Cash Flow'!E26 -> 1065883 | F7: ='Cash Flow'!F26 -> 869043 | G7: ='Cash Flow'!G26 -> 1530954 | H7: ='Cash Flow'!H26 -> 1644139 | I7: ='Cash Flow'!I26 -> 1761156
B8: Net earnings | D8: =Table123[[#This Row],[FY2021]] -> 564348 | E8: =Table123[[#This Row],[FY2022]] -> 663169 | F8: =Table123[[#This Row],[FY2023]] -> 801863 | G8: =Table123[[#This Row],[FY2024]] -> 1010460 | H8: =Table123[[#This Row],[FY2025]] -> 1168545 | I8: =Table123[[#This Row],[FY2026]] -> 1309438
B9: Cash conversion (OCF / Net earnings) | D9: =D7/D8 -> 1.5745994 | E9: =E7/E8 -> 1.607257 | F9: =F7/F8 -> 1.0837799 | G9: =G7/G8 -> 1.515106 | H9: =H7/H8 -> 1.4069967 | I9: =I7/I8 -> 1.3449709
B11: Capex, such as property, plant and equipment | D11: ='Cash Flow'!D32 -> -140040 | E11: ='Cash Flow'!E32 -> -136772 | F11: ='Cash Flow'!F32 -> -134049 | G11: ='Cash Flow'!G32 -> -252673 | H11: ='Cash Flow'!H32 -> -212828 | I11: ='Cash Flow'!I32 -> -248747
B12: Capex, such as intangible assets | D12: ='Cash Flow'!D33 -> -27797 | E12: ='Cash Flow'!E33 -> -22740 | F12: ='Cash Flow'!F33 -> -22778 | G12: ='Cash Flow'!G33 -> -26091 | H12: ='Cash Flow'!H33 -> -30622 | I12: ='Cash Flow'!I33 -> -24034
B13: Total capex | D13: =D11+D12 -> -167837 | E13: =E11+E12 -> -159512 | F13: =F11+F12 -> -156827 | G13: =G11+G12 -> -278764 | H13: =H11+H12 -> -243450 | I13: =I11+I12 -> -272781
B14: Free cash flow (OCF - Total capex) | D14: =D7+D13 -> 720785 | E14: =E7+E13 -> 906371 | F14: =F7+F13 -> 712216 | G14: =G7+G13 -> 1252190 | H14: =H7+H13 -> 1400689 | I14: =I7+I13 -> 1488375
B15: FCF margin (FCF / Sales) | D15: =D14/'Income Statement'!D7 -> 0.17902102 | E15: =E14/'Income Statement'!E7 -> 0.20928677 | F15: =F14/'Income Statement'!F7 -> 0.14095636 | G15: =G14/'Income Statement'!G7 -> 0.21341669 | H15: =H14/'Income Statement'!H7 -> 0.21840906 | I15: =I14/'Income Statement'!I7 -> 0.2051303
B16: Capex / Sales | D16: =-D13/'Income Statement'!D7 -> 0.041685594 | E16: =-E13/'Income Statement'!E7 -> 0.036832326 | F16: =-F13/'Income Statement'!F7 -> 0.031038005 | G16: =-G13/'Income Statement'!G7 -> 0.047511073 | H16: =-H13/'Income Statement'!H7 -> 0.037961094 | I16: =-I13/'Income Statement'!I7 -> 0.037595128
B18: Memo: net lease liability principal repayments (financing activities) | D18: ='Cash Flow'!D51 -> -163804 | E18: ='Cash Flow'!E51 -> -183285 | F18: ='Cash Flow'!F51 -> -253566 | G18: ='Cash Flow'!G51 -> -284836 | H18: ='Cash Flow'!H51 -> -317829 | I18: ='Cash Flow'!I51 -> -390333
B19: Memo: share repurchases + treasury share activity | D19: ='Cash Flow'!D54+'Cash Flow'!D55 -> -87042 | E19: ='Cash Flow'!E54+'Cash Flow'!E55 -> -1059918 | F19: ='Cash Flow'!F54+'Cash Flow'!F55 -> -688996 | G19: ='Cash Flow'!G54+'Cash Flow'!G55 -> -655869 | H19: ='Cash Flow'!H54+'Cash Flow'!H55 -> -1090712 | I19: ='Cash Flow'!I54+'Cash Flow'!I55 -> -864384
B20: Memo: dividends paid | D20: ='Cash Flow'!D53 -> -54770 | E20: ='Cash Flow'!E53 -> -60464 | F20: ='Cash Flow'!F53 -> -62975 | G20: ='Cash Flow'!G53 -> -76131 | H20: ='Cash Flow'!H53 -> -97244 | I20: ='Cash Flow'!I53 -> -113196
B21: FCF less dividends & buybacks (cash left after shareholder returns) | D21: =D14+D19+D20 -> 578973 | E21: =E14+E19+E20 -> -214011 | F21: =F14+F19+F20 -> -39755 | G21: =G14+G19+G20 -> 520190 | H21: =H14+H19+H20 -> 212733 | I21: =I14+I19+I20 -> 510795

Sheet Forecast + Valuation
B2: Dollarama Inc.
B3: Forecast & Simplified DCF Valuation (Illustrative)
B4: This is a simplified, unlevered-FCF DCF for practice/demonstration => this is not investment advice and not a substitute for a full model. So, keep that in mind.
B5: (CAD $ thousands) | D5: FY2021 | E5: FY2022 | F5: FY2023 | G5: FY2024 | H5: FY2025 | I5: FY2026 | J5: FY2027E | K5: FY2028E | L5: FY2029E
B6: Historical reference (for calibrating assumptions below)
B7: Revenue 5-yr CAGR (FY2021→FY2026) | D7: =('Income Statement'!I7/'Income Statement'!D7)^(1/5)-1 -> 0.12500944
B8: Revenue 3-yr CAGR (FY2023→FY2026) | D8: =('Income Statement'!I7/'Income Statement'!F7)^(1/3)-1 -> 0.1281976
B9: Average operating margin, FY2024–FY2026 | D9: =AVERAGE(Ratio!D14:I14) -> 0.24429343
B10: Average effective tax rate, FY2024–FY2026 | D10: =AVERAGE(('Income Statement'!G17/'Income Statement'!G16), ('Income Statement'!H17/'Income Statement'!H16), ('Income Statement'!I17/'Income Statement'!I16)) -> 0.25145075
B11: Average D&A % of sales, FY2024–FY2026 | D11: =AVERAGE(Table12[[#This Row],[FY2024]]/'Income Statement'!G7, Table12[[#This Row],[FY2025]]/'Income Statement'!H7, Table12[[#This Row],[FY2026]]/'Income Statement'!I7) -> 0.059386324
B12: Average total capex % of sales, FY2024–FY2026 | D12: =AVERAGE('CF Quality'!G16:I16) -> 0.041022432
B14: Assumptions
B15: Revenue growth rate | D15: 0.08
B16: Operating margin | D16: 0.265
B17: Effective tax rate | D17: 0.25
B18: D&A % of sales | D18: 0.06
B19: Capex % of sales | D19: 0.04
B20: Change in net working capital (% of incremental sales) | D20: 0
B21: Terminal (perpetuity) growth rate | D21: 0.025
B23: Cost of equity (CAPM)
B24: Risk-free rate (Canada 10-yr government bond yield) | D24: 0.0385
B25: Equity beta | D25: 0.5
B26: Equity risk premium | D26: 0.055
B27: Cost of Equity | D27: =D24+D25*D26 -> 0.066
B29: Cost of debt
B30: Pre-tax cost of debt | D30: 0.0267
B31: After-tax cost of debt | D31: 0.02
B32: Implied pre-tax cost of lease financing (lease liab. Interest / total lease liab.) | D32: ='Cash Flow'!I64/('Financial Position'!I43+'Financial Position'!I37) -> 0.035765373
B33: After-tax cost of lease financing | D33: 0.027
B35: Cost of debt
B36: Recent share price (CAD $) | D36: 172.46
B37: Market value of equity (share price x diluted shares) | D37: =D36*Table12[[#This Row],[FY2026]] -> 47716923
B38: Market value of debt (book value used as a proxy) | D38: ='Financial Position'!I42+'Financial Position'!I36 -> 2625121
B39: Market value of lease liabilities (book value) | D39: ='Financial Position'!I37+'Financial Position'!I43 -> 2770473
B40: Total capital | D40: =SUM(D37:D39) -> 53112517
B41: Weight (equity) | D41: =D37/D40 -> 0.89841201
B42: Weight (debt) | D42: =D38/D40 -> 0.049425656
B43: Weight (lease liabilities) | D43: =D39/D40 -> 0.052162337
B45: WACC estimation | D45: =(D41*D27)+(D42*D31)+(D43*D33) -> 0.061692089
B47: Projected income statement & unlevered free cash flow
B48: Sales | D48: ='Income Statement'!D7 -> 4026259 | E48: ='Income Statement'!E7 -> 4330761 | F48: ='Income Statement'!F7 -> 5052741 | G48: ='Income Statement'!G7 -> 5867348 | H48: ='Income Statement'!H7 -> 6413145 | I48: ='Income Statement'!I7 -> 7255754 | J48: =I48*(1+$D$15) -> 7836214.3 | K48: =J48*(1+$D$15) -> 8463111.5 | L48: =K48*(1+$D$15) -> 9140160.4
B49: EBIT (Sales × Operating margin) | J49: =J48*$D$16 -> 2076596.8 | K49: =K48*$D$16 -> 2242724.5 | L49: =L48*$D$16 -> 2422142.5
B50: Less: taxes on EBIT | J50: =-J49*$D$17 -> -519149.2 | K50: =-K49*$D$17 -> -560681.13 | L50: =-L49*$D$17 -> -605535.63
B51: NOPAT | J51: =J49+J50 -> 1557447.6 | K51: =K49+K50 -> 1682043.4 | L51: =L49+L50 -> 1816606.9
B52: Plus: D&A | J52: =J48*$D$18 -> 470172.86 | K52: =K48*$D$18 -> 507786.69 | L52: =L48*$D$18 -> 548409.62
B53: Less: Capex | J53: =-J48*$D$19 -> -313448.57 | K53: =-K48*$D$19 -> -338524.46 | L53: =-L48*$D$19 -> -365606.42
B54: Less: Increase in net working capital | J54: =-(J48-I48)*$D$20 -> 0 | K54: =-(K48-J48)*$D$20 -> 0 | L54: =-(L48-K48)*$D$20 -> 0
B55: Unlevered free cash flow | J55: =J51+J52+J53+J54 -> 1714171.9 | K55: =K51+K52+K53+K54 -> 1851305.6 | L55: =L51+L52+L53+L54 -> 1999410.1
B57: Simplified DCF
B58: Discount factor (1 / (1+WACC)^t) | J58: =1/(1+WACC)^1 -> 0.94189267 | K58: =1/(1+WACC)^2 -> 0.88716181 | L58: =1/(1+WACC)^3 -> 0.83561121
B59: PV of unlevered FCF | J59: =J55*J58 -> 1614565.9 | K59: =K55*K58 -> 1642407.7 | L59: =L55*L58 -> 1670729.5
B60: Sum of PV of explicit-period FCF (FY2027E-FY2029E) | D60: =SUM(J59:L59) -> 4927703.1
B61: Terminal value (Gordon growth, end of FY2029E) | D61: =L55*(1+$D$21)/(WACC-$D$21) -> 55853875
B62: PV of terminal value | D62: =D61*L58 -> 46672124
B63: Enterprise value | D63: =D60+D62 -> 51599827
B64: Less: Net debt (interest-bearing debt − cash, FY2026) | D64: =-('Financial Position'!I32+'Financial Position'!I36+'Financial Position'!I42+'Financial Position'!I37+'Financial Position'!I43-'Financial Position'!I9) -> -5064025
B65: Implied equity value | D65: =D63+D64 -> 46535802
B66: Diluted shares outstanding (FY2026, held flat) | D66: ='Income Statement'!I37 -> 276684
B67: Implied value per share | D67: =D65/D66 -> 168.19116
B69: Sensitivity - implied value per share by WACC (rows) × terminal growth rate (columns)
B71: WACC ↓ / Terminal growth → | D71: =$D$21+(-0.01) -> 0.015 | E71: =$D$21+(-0.005) -> 0.02 | F71: =$D$21+(0) -> 0.025 | G71: =$D$21+(0.005) -> 0.03 | H71: =$D$21+(0.01) -> 0.035
B72: =WACC+(-0.01) -> 0.051692089 | D72: =((J$55/(1+$B72)^1+K$55/(1+$B72)^2+L$55/(1+$B72)^3+(L$55*(1+D$71)/($B72-D$71))/(1+$B72)^3)+$D$64)/$D$66 -> 171.69855 | E72: =((J$55/(1+$B72)^1+K$55/(1+$B72)^2+L$55/(1+$B72)^3+(L$55*(1+E$71)/($B72-E$71))/(1+$B72)^3)+$D$64)/$D$66 -> 199.79085 | F72: =((J$55/(1+$B72)^1+K$55/(1+$B72)^2+L$55/(1+$B72)^3+(L$55*(1+F$71)/($B72-F$71))/(1+$B72)^3)+$D$64)/$D$66 -> 238.40773 | G72: =((J$55/(1+$B72)^1+K$55/(1+$B72)^2+L$55/(1+$B72)^3+(L$55*(1+G$71)/($B72-G$71))/(1+$B72)^3)+$D$64)/$D$66 -> 294.8269 | H72: =((J$55/(1+$B72)^1+K$55/(1+$B72)^2+L$55/(1+$B72)^3+(L$55*(1+H$71)/($B72-H$71))/(1+$B72)^3)+$D$64)/$D$66 -> 385.04602
B73: =WACC+(-0.005) -> 0.056692089 | D73: =((J$55/(1+$B73)^1+K$55/(1+$B73)^2+L$55/(1+$B73)^3+(L$55*(1+D$71)/($B73-D$71))/(1+$B73)^3)+$D$64)/$D$66 -> 148.77982 | E73: =((J$55/(1+$B73)^1+K$55/(1+$B73)^2+L$55/(1+$B73)^3+(L$55*(1+E$71)/($B73-E$71))/(1+$B73)^3)+$D$64)/$D$66 -> 169.93247 | F73: =((J$55/(1+$B73)^1+K$55/(1+$B73)^2+L$55/(1+$B73)^3+(L$55*(1+F$71)/($B73-F$71))/(1+$B73)^3)+$D$64)/$D$66 -> 197.75955 | G73: =((J$55/(1+$B73)^1+K$55/(1+$B73)^2+L$55/(1+$B73)^3+(L$55*(1+G$71)/($B73-G$71))/(1+$B73)^3)+$D$64)/$D$66 -> 236.01185 | H73: =((J$55/(1+$B73)^1+K$55/(1+$B73)^2+L$55/(1+$B73)^3+(L$55*(1+H$71)/($B73-H$71))/(1+$B73)^3)+$D$64)/$D$66 -> 291.89836
B74: =WACC+(0) -> 0.061692089 | D74: =((J$55/(1+$B74)^1+K$55/(1+$B74)^2+L$55/(1+$B74)^3+(L$55*(1+D$71)/($B74-D$71))/(1+$B74)^3)+$D$64)/$D$66 -> 130.77106 | E74: =((J$55/(1+$B74)^1+K$55/(1+$B74)^2+L$55/(1+$B74)^3+(L$55*(1+E$71)/($B74-E$71))/(1+$B74)^3)+$D$64)/$D$66 -> 147.23727 | F74: =((J$55/(1+$B74)^1+K$55/(1+$B74)^2+L$55/(1+$B74)^3+(L$55*(1+F$71)/($B74-F$71))/(1+$B74)^3)+$D$64)/$D$66 -> 168.19116 | G74: =((J$55/(1+$B74)^1+K$55/(1+$B74)^2+L$55/(1+$B74)^3+(L$55*(1+G$71)/($B74-G$71))/(1+$B74)^3)+$D$64)/$D$66 -> 195.75675 | H74: =((J$55/(1+$B74)^1+K$55/(1+$B74)^2+L$55/(1+$B74)^3+(L$55*(1+H$71)/($B74-H$71))/(1+$B74)^3)+$D$64)/$D$66 -> 233.6496
B75: =WACC+(0.005) -> 0.066692089 | D75: =((J$55/(1+$B75)^1+K$55/(1+$B75)^2+L$55/(1+$B75)^3+(L$55*(1+D$71)/($B75-D$71))/(1+$B75)^3)+$D$64)/$D$66 -> 116.24747 | E75: =((J$55/(1+$B75)^1+K$55/(1+$B75)^2+L$55/(1+$B75)^3+(L$55*(1+E$71)/($B75-E$71))/(1+$B75)^3)+$D$64)/$D$66 -> 129.40403 | F75: =((J$55/(1+$B75)^1+K$55/(1+$B75)^2+L$55/(1+$B75)^3+(L$55*(1+F$71)/($B75-F$71))/(1+$B75)^3)+$D$64)/$D$66 -> 145.71623 | G75: =((J$55/(1+$B75)^1+K$55/(1+$B75)^2+L$55/(1+$B75)^3+(L$55*(1+G$71)/($B75-G$71))/(1+$B75)^3)+$D$64)/$D$66 -> 166.47414 | H75: =((J$55/(1+$B75)^1+K$55/(1+$B75)^2+L$55/(1+$B75)^3+(L$55*(1+H$71)/($B75-H$71))/(1+$B75)^3)+$D$64)/$D$66 -> 193.78192
B76: =WACC+(0.01) -> 0.071692089 | D76: =((J$55/(1+$B76)^1+K$55/(1+$B76)^2+L$55/(1+$B76)^3+(L$55*(1+D$71)/($B76-D$71))/(1+$B76)^3)+$D$64)/$D$66 -> 104.2869 | E76: =((J$55/(1+$B76)^1+K$55/(1+$B76)^2+L$55/(1+$B76)^3+(L$55*(1+E$71)/($B76-E$71))/(1+$B76)^3)+$D$64)/$D$66 -> 115.02188 | F76: =((J$55/(1+$B76)^1+K$55/(1+$B76)^2+L$55/(1+$B76)^3+(L$55*(1+F$71)/($B76-F$71))/(1+$B76)^3)+$D$64)/$D$66 -> 128.05596 | G76: =((J$55/(1+$B76)^1+K$55/(1+$B76)^2+L$55/(1+$B76)^3+(L$55*(1+G$71)/($B76-G$71))/(1+$B76)^3)+$D$64)/$D$66 -> 144.21631 | H76: =((J$55/(1+$B76)^1+K$55/(1+$B76)^2+L$55/(1+$B76)^3+(L$55*(1+H$71)/($B76-H$71))/(1+$B76)^3)+$D$64)/$D$66 -> 164.78098

Sheet Financial Position
C2: Dollarama Inc.
C3: Consolidated Statements of Financial Position 2026-2021
C4: (Expressed in thousands of Canadian dollars)
C6: LineItem | D6: FY2021 | E6: FY2022 | F6: FY2023 | G6: FY2024 | H6: FY2025 | I6: FY2026
C7: ='FP-2026_2022'!B2 -> Assets
C8: ='FP-2026_2022'!B3 -> Current assets
C9: ='FP-2026_2022'!B4 -> Cash and cash equivalents | D9: ='FP-2026_2022'!C4 -> 439144 | E9: ='FP-2026_2022'!D4 -> 71058 | F9: ='FP-2026_2022'!E4 -> 101261 | G9: ='FP-2026_2022'!F4 -> 313915 | H9: ='FP-2026_2022'!G4 -> 122685 | I9: ='FP-2026_2022'!H4 -> 331569
C10: ='FP-2026_2022'!B5 -> Accounts receivable | D10: ='FP-2026_2022'!C5 -> 20546 | E10: ='FP-2026_2022'!D5 -> 26260 | F10: ='FP-2026_2022'!E5 -> 56290 | G10: ='FP-2026_2022'!F5 -> 32474 | H10: ='FP-2026_2022'!G5 -> 46638 | I10: ='FP-2026_2022'!H5 -> 38500
C11: ='FP-2026_2022'!B6 -> Income taxes receivable | D11: ='FP-2026_2022'!C6 -> 0 | E11: ='FP-2026_2022'!D6 -> 0 | F11: ='FP-2026_2022'!E6 -> 0 | G11: ='FP-2026_2022'!F6 -> 0 | H11: ='FP-2026_2022'!G6 -> 0 | I11: ='FP-2026_2022'!H6 -> 559
C12: ='FP-2026_2022'!B7 -> Distributions receivable from equity-accounted investments | D12: ='FP-2026_2022'!C7 -> 0 | E12: ='FP-2026_2022'!D7 -> 0 | F12: ='FP-2026_2022'!E7 -> 0 | G12: ='FP-2026_2022'!F7 -> 26906 | H12: ='FP-2026_2022'!G7 -> 54620 | I12: ='FP-2026_2022'!H7 -> 0
C13: ='FP-2026_2022'!B8 -> Prepaid expenses | D13: ='FP-2026_2022'!C8 -> 9549 | E13: ='FP-2026_2022'!D8 -> 13135 | F13: ='FP-2026_2022'!E8 -> 23462 | G13: ='FP-2026_2022'!F8 -> 13668 | H13: ='FP-2026_2022'!G8 -> 13911 | I13: ='FP-2026_2022'!H8 -> 38452
C14: ='FP-2026_2022'!B9 -> Inventories | D14: ='FP-2026_2022'!C9 -> 630655 | E14: ='FP-2026_2022'!D9 -> 590927 | F14: ='FP-2026_2022'!E9 -> 957172 | G14: ='FP-2026_2022'!F9 -> 916812 | H14: ='FP-2026_2022'!G9 -> 921095 | I14: ='FP-2026_2022'!H9 -> 1103175
C15: ='FP-2026_2022'!B10 -> Derivative financial instruments | D15: ='FP-2026_2022'!C10 -> 468 | E15: ='FP-2026_2022'!D10 -> 15987 | F15: ='FP-2026_2022'!E10 -> 18762 | G15: ='FP-2026_2022'!F10 -> 5318 | H15: ='FP-2026_2022'!G10 -> 42331 | I15: ='FP-2026_2022'!H10 -> 9734
C16: ='FP-2026_2022'!B11 -> Total current assets | D16: =SUM(D9:D15) -> 1100362 | E16: =SUM(E9:E15) -> 717367 | F16: =SUM(F9:F15) -> 1156947 | G16: =SUM(G9:G15) -> 1309093 | H16: =SUM(H9:H15) -> 1201280 | I16: =SUM(I9:I15) -> 1521989
C18: ='FP-2026_2022'!B12 -> Non-current assets
C19: ='FP-2026_2022'!B13 -> Right-of-use assets | D19: ='FP-2026_2022'!C13 -> 1344639 | E19: ='FP-2026_2022'!D13 -> 1480255 | F19: ='FP-2026_2022'!E13 -> 1699755 | G19: ='FP-2026_2022'!F13 -> 1788550 | H19: ='FP-2026_2022'!G13 -> 2109445 | I19: ='FP-2026_2022'!H13 -> 2397209
C20: ='FP-2026_2022'!B14 -> Property, plant and equipment | D20: ='FP-2026_2022'!C14 -> 709469 | E20: ='FP-2026_2022'!D14 -> 761876 | F20: ='FP-2026_2022'!E14 -> 802750 | G20: ='FP-2026_2022'!F14 -> 950994 | H20: ='FP-2026_2022'!G14 -> 1046390 | I20: ='FP-2026_2022'!H14 -> 1258499
C21: ='FP-2026_2022'!B15 -> Intangible assets | D21: ='FP-2026_2022'!C15 -> 161791 | E21: ='FP-2026_2022'!D15 -> 164066 | F21: ='FP-2026_2022'!E15 -> 164654 | G21: ='FP-2026_2022'!F15 -> 167835 | H21: ='FP-2026_2022'!G15 -> 180689 | I21: ='FP-2026_2022'!H15 -> 178281
C22: ='FP-2026_2022'!B16 -> Derivative financial instruments | D22: ='FP-2026_2022'!C16 -> 314 | E22: ='FP-2026_2022'!D16 -> 290 | F22: ='FP-2026_2022'!E16 -> 0 | G22: ='FP-2026_2022'!F16 -> 0 | H22: ='FP-2026_2022'!G16 -> 0 | I22: ='FP-2026_2022'!H16 -> 0
C23: ='FP-2026_2022'!B17 -> Goodwill | D23: ='FP-2026_2022'!C17 -> 727782 | E23: ='FP-2026_2022'!D17 -> 727782 | F23: ='FP-2026_2022'!E17 -> 727782 | G23: ='FP-2026_2022'!F17 -> 727782 | H23: ='FP-2026_2022'!G17 -> 727782 | I23: ='FP-2026_2022'!H17 -> 801709
C24: ='FP-2026_2022'!B18 -> Equity-accounted investments | D24: ='FP-2026_2022'!C18 -> 179389 | E24: ='FP-2026_2022'!D18 -> 211926 | F24: ='FP-2026_2022'!E18 -> 267768 | G24: ='FP-2026_2022'!F18 -> 319353 | H24: ='FP-2026_2022'!G18 -> 1131650 | I24: ='FP-2026_2022'!H18 -> 1285105
C25: ='FP-2026_2022'!B19 -> Derivative on equity-accounted investments | D25: ='FP-2026_2022'!C19 -> 0 | E25: ='FP-2026_2022'!D19 -> 0 | F25: ='FP-2026_2022'!E19 -> 0 | G25: ='FP-2026_2022'!F19 -> 0 | H25: ='FP-2026_2022'!G19 -> 85356 | I25: ='FP-2026_2022'!H19 -> 89846
C26: ='FP-2026_2022'!B20 -> Deferred income taxes | D26: ='FP-2026_2022'!C20 -> 0 | E26: ='FP-2026_2022'!D20 -> 0 | F26: ='FP-2026_2022'!E20 -> 0 | G26: ='FP-2026_2022'!F20 -> 0 | H26: ='FP-2026_2022'!G20 -> 0 | I26: ='FP-2026_2022'!H20 -> 25714
C27: ='FP-2026_2022'!B21 -> Total assets | D27: =SUM(D19:D26)+D16 -> 4223746 | E27: =SUM(E19:E26)+E16 -> 4063562 | F27: =SUM(F19:F26)+F16 -> 4819656 | G27: =SUM(G19:G26)+G16 -> 5263607 | H27: =SUM(H19:H26)+H16 -> 6482592 | I27: =SUM(I19:I26)+I16 -> 7558352
C29: ='FP-2026_2022'!B22 -> Liabilities and shareholders' equity
C30: ='FP-2026_2022'!B23 -> Current liabilities
C31: ='FP-2026_2022'!B24 -> Accounts payable and accrued liabilities | D31: ='FP-2026_2022'!C24 -> 253072 | E31: ='FP-2026_2022'!D24 -> 283125 | F31: ='FP-2026_2022'!E24 -> 336862 | G31: ='FP-2026_2022'!F24 -> 334357 | H31: ='FP-2026_2022'!G24 -> 354900 | I31: ='FP-2026_2022'!H24 -> 461766
C32: ='FP-2026_2022'!B25 -> Short-term borrowings | D32: ='FP-2026_2022'!C25 -> 0 | E32: ='FP-2026_2022'!D25 -> 89386 | F32: ='FP-2026_2022'!E25 -> 0 | G32: ='FP-2026_2022'!F25 -> 0 | H32: ='FP-2026_2022'!G25 -> 0 | I32: ='FP-2026_2022'!H25 -> 0
C33: ='FP-2026_2022'!B26 -> Dividend payable | D33: ='FP-2026_2022'!C26 -> 14583 | E33: ='FP-2026_2022'!D26 -> 14891 | F33: ='FP-2026_2022'!E26 -> 15828 | G33: ='FP-2026_2022'!F26 -> 19827 | H33: ='FP-2026_2022'!G26 -> 25558 | I33: ='FP-2026_2022'!H26 -> 28941
C34: ='FP-2026_2022'!B27 -> Derivative financial instruments | D34: ='FP-2026_2022'!C27 -> 25821 | E34: ='FP-2026_2022'!D27 -> 3435 | F34: ='FP-2026_2022'!E27 -> 8490 | G34: ='FP-2026_2022'!F27 -> 3681 | H34: ='FP-2026_2022'!G27 -> 0 | I34: ='FP-2026_2022'!H27 -> 17145
C35: ='FP-2026_2022'!B28 -> Income taxes payable | D35: ='FP-2026_2022'!C28 -> 12975 | E35: ='FP-2026_2022'!D28 -> 62516 | F35: ='FP-2026_2022'!E28 -> 72572 | G35: ='FP-2026_2022'!F28 -> 63998 | H35: ='FP-2026_2022'!G28 -> 81372 | I35: ='FP-2026_2022'!H28 -> 64309
C36: ='FP-2026_2022'!B29 -> Current portion of long-term debt | D36: ='FP-2026_2022'!C29 -> 832821 | E36: ='FP-2026_2022'!D29 -> 257674 | F36: ='FP-2026_2022'!E29 -> 510315 | G36: ='FP-2026_2022'!F29 -> 21460 | H36: ='FP-2026_2022'!G29 -> 273771 | I36: ='FP-2026_2022'!H29 -> 398275
C37: ='FP-2026_2022'!B30 -> Current portion of lease liabilities | D37: ='FP-2026_2022'!C30 -> 181893 | E37: ='FP-2026_2022'!D30 -> 200864 | F37: ='FP-2026_2022'!E30 -> 218807 | G37: ='FP-2026_2022'!F30 -> 234523 | H37: ='FP-2026_2022'!G30 -> 278705 | I37: ='FP-2026_2022'!H30 -> 377743
C38: ='FP-2026_2022'!B31 -> Total current liabilities | D38: =SUM(D31:D37) -> 1321165 | E38: =SUM(E31:E37) -> 911891 | F38: =SUM(F31:F37) -> 1162874 | G38: =SUM(G31:G37) -> 677846 | H38: =SUM(H31:H37) -> 1014306 | I38: =SUM(I31:I37) -> 1348179
C40: ='FP-2026_2022'!B32 -> Non-current liabilities
C41: ='FP-2026_2022'!B33 -> Non-current provisions and other liabilities | D41: ='FP-2026_2022'!C33 -> 0 | E41: ='FP-2026_2022'!D33 -> 0 | F41: ='FP-2026_2022'!E33 -> 0 | G41: ='FP-2026_2022'!F33 -> 0 | H41: ='FP-2026_2022'!G33 -> 0 | I41: ='FP-2026_2022'!H33 -> 31982
C42: ='FP-2026_2022'!B34 -> Non-current portion of long-term debt | D42: ='FP-2026_2022'!C34 -> 1044079 | E42: ='FP-2026_2022'!D34 -> 1539240 | F42: ='FP-2026_2022'!E34 -> 1741588 | G42: ='FP-2026_2022'!F34 -> 2242934 | H42: ='FP-2026_2022'!G34 -> 2008908 | I42: ='FP-2026_2022'!H34 -> 2226846
C43: ='FP-2026_2022'!B35 -> Non-current portion of lease liabilities | D43: ='FP-2026_2022'!C35 -> 1401769 | E43: ='FP-2026_2022'!D35 -> 1526564 | F43: ='FP-2026_2022'!E35 -> 1741936 | G43: ='FP-2026_2022'!F35 -> 1834706 | H43: ='FP-2026_2022'!G35 -> 2148272 | I43: ='FP-2026_2022'!H35 -> 2392730
C44: ='FP-2026_2022'!B36 -> Deferred income taxes | D44: ='FP-2026_2022'!C36 -> 121879 | E44: ='FP-2026_2022'!D36 -> 151901 | F44: ='FP-2026_2022'!E36 -> 144848 | G44: ='FP-2026_2022'!F36 -> 127273 | H44: ='FP-2026_2022'!G36 -> 122848 | I44: ='FP-2026_2022'!H36 -> 102727
C45: ='FP-2026_2022'!B37 -> Total liabilities | D45: =SUM(D41:D44)+D38 -> 3888892 | E45: =SUM(E41:E44)+E38 -> 4129596 | F45: =SUM(F41:F44)+F38 -> 4791246 | G45: =SUM(G41:G44)+G38 -> 4882759 | H45: =SUM(H41:H44)+H38 -> 5294334 | I45: =SUM(I41:I44)+I38 -> 6102464
C47: ='FP-2026_2022'!B38 -> Shareholders' equity
C48: ='FP-2026_2022'!B39 -> Share capital | D48: ='FP-2026_2022'!C39 -> 485487 | E48: ='FP-2026_2022'!D39 -> 479446 | F48: ='FP-2026_2022'!E39 -> 488074 | G48: ='FP-2026_2022'!F39 -> 523125 | H48: ='FP-2026_2022'!G39 -> 1275702 | I48: ='FP-2026_2022'!H39 -> 1266750
C49: ='FP-2026_2022'!B40 -> Treasury shares | D49: ='FP-2026_2022'!C40 -> 0 | E49: ='FP-2026_2022'!D40 -> 0 | F49: ='FP-2026_2022'!E40 -> 0 | G49: ='FP-2026_2022'!F40 -> 0 | H49: ='FP-2026_2022'!G40 -> -20000 | I49: ='FP-2026_2022'!H40 -> -29970
C50: ='FP-2026_2022'!B41 -> Contributed surplus | D50: ='FP-2026_2022'!C41 -> 28527 | E50: ='FP-2026_2022'!D41 -> 32924 | F50: ='FP-2026_2022'!E41 -> 42678 | G50: ='FP-2026_2022'!F41 -> 49539 | H50: ='FP-2026_2022'!G41 -> 51718 | I50: ='FP-2026_2022'!H41 -> 57572
C51: ='FP-2026_2022'!B42 -> Retained earnings (Deficit) | D51: ='FP-2026_2022'!C42 -> -149983 | E51: ='FP-2026_2022'!D42 -> -578079 | F51: ='FP-2026_2022'!E42 -> -514078 | G51: ='FP-2026_2022'!F42 -> -226547 | H51: ='FP-2026_2022'!G42 -> -225301 | I51: ='FP-2026_2022'!H42 -> 128858
C52: ='FP-2026_2022'!B43 -> Accumulated other comprehensive income | D52: ='FP-2026_2022'!C43 -> -29177 | E52: ='FP-2026_2022'!D43 -> -325 | F52: ='FP-2026_2022'!E43 -> 11736 | G52: ='FP-2026_2022'!F43 -> 34731 | H52: ='FP-2026_2022'!G43 -> 106139 | I52: ='FP-2026_2022'!H43 -> 32678
C53: ='FP-2026_2022'!B44 -> Total shareholders' equity | D53: =SUM(D48:D52) -> 334854 | E53: =SUM(E48:E52) -> -66034 | F53: =SUM(F48:F52) -> 28410 | G53: =SUM(G48:G52) -> 380848 | H53: =SUM(H48:H52) -> 1188258 | I53: =SUM(I48:I52) -> 1455888
C55: ='FP-2026_2022'!B45 -> Total liabilities and shareholders' equity | D55: =D53+D45 -> 4223746 | E55: =E53+E45 -> 4063562 | F55: =F53+F45 -> 4819656 | G55: =G53+G45 -> 5263607 | H55: =H53+H45 -> 6482592 | I55: =I53+I45 -> 7558352

Sheet Income Statement
C2: Dollarama Inc.
C3: Consolidated Income Statement 2026-2021
C4: (Expressed in thousands of Canadian dollars)
C6: Line Item (CAD $ Thousands) | D6: FY2021 | E6: FY2022 | F6: FY2023 | G6: FY2024 | H6: FY2025 | I6: FY2026
C7: Sales | D7: ='Data-Income Statement'!C31 -> 4026259 | E7: ='Data-Income Statement'!D31 -> 4330761 | F7: ='Data-Income Statement'!E31 -> 5052741 | G7: ='Data-Income Statement'!F31 -> 5867348 | H7: ='Data-Income Statement'!G2 -> 6413145 | I7: ='Data-Income Statement'!H2 -> 7255754
C8: Cost of sales | D8: ='Data-Income Statement'!C32 -> 2261248 | E8: ='Data-Income Statement'!D32 -> 2428536 | F8: ='Data-Income Statement'!E32 -> 2854535 | G8: ='Data-Income Statement'!F32 -> 3253907 | H8: ='Data-Income Statement'!G3 -> 3519399 | I8: ='Data-Income Statement'!H3 -> 3987089
C9: Gross profit | D9: =D7-D8 -> 1765011 | E9: =E7-E8 -> 1902225 | F9: =F7-F8 -> 2198206 | G9: =G7-G8 -> 2613441 | H9: =H7-H8 -> 2893746 | I9: =I7-I8 -> 3268665
C10: General, administrative and store operating expenses | D10: ='Data-Income Statement'!C34 -> 654032 | E10: ='Data-Income Statement'!D34 -> 652832 | F10: ='Data-Income Statement'!E34 -> 720312 | G10: ='Data-Income Statement'!F34 -> 844871 | H10: ='Data-Income Statement'!G5 -> 930168 | I10: ='Data-Income Statement'!H5 -> 1093289
C11: Depreciation and amortization | D11: ='Data-Income Statement'!C35 -> 269633 | E11: ='Data-Income Statement'!D35 -> 297960 | F11: ='Data-Income Statement'!E35 -> 331792 | G11: ='Data-Income Statement'!F35 -> 348142 | H11: ='Data-Income Statement'!G6 -> 382805 | I11: ='Data-Income Statement'!H6 -> 429053
C12: Share of net earnings of equity-accounted investments | D12: ='Data-Income Statement'!C36 -> -19654 | E12: ='Data-Income Statement'!D36 -> -33184 | F12: ='Data-Income Statement'!E36 -> -45399 | G12: ='Data-Income Statement'!F36 -> -75293 | H12: ='Data-Income Statement'!G7 -> -129905 | I12: ='Data-Income Statement'!H7 -> -191536
C13: Operating income | D13: =D9-SUM(D10:D12) -> 861000 | E13: =E9-SUM(E10:E12) -> 984617 | F13: =F9-SUM(F10:F12) -> 1191501 | G13: =G9-SUM(G10:G12) -> 1495721 | H13: =H9-SUM(H10:H12) -> 1710678 | I13: =I9-SUM(I10:I12) -> 1937859
C14: Unrealized gain from derivative on equity-accounted investments | D14: ='Data-Income Statement'!C9 -> 0 | E14: ='Data-Income Statement'!D9 -> 0 | F14: ='Data-Income Statement'!E9 -> 0 | G14: ='Data-Income Statement'!F9 -> 0 | H14: ='Data-Income Statement'!G9 -> 0 | I14: ='Data-Income Statement'!H9 -> -10348
C15: Net financing costs | D15: ='Data-Income Statement'!C38 -> 95646 | E15: ='Data-Income Statement'!D38 -> 91216 | F15: ='Data-Income Statement'!E38 -> 115394 | G15: ='Data-Income Statement'!F38 -> 144842 | H15: ='Data-Income Statement'!G10 -> 163782 | I15: ='Data-Income Statement'!H10 -> 184020
C16: Earnings before income taxes | D16: =D13-SUM(D14:D15) -> 765354 | E16: =E13-SUM(E14:E15) -> 893401 | F16: =F13-SUM(F14:F15) -> 1076107 | G16: =G13-SUM(G14:G15) -> 1350879 | H16: =H13-SUM(H14:H15) -> 1546896 | I16: =I13-SUM(I14:I15) -> 1764187
C17: Income taxes | D17: ='Data-Income Statement'!C40 -> 201006 | E17: ='Data-Income Statement'!D40 -> 230232 | F17: ='Data-Income Statement'!E40 -> 274244 | G17: ='Data-Income Statement'!F40 -> 340419 | H17: ='Data-Income Statement'!G12 -> 378351 | I17: ='Data-Income Statement'!H12 -> 454749
C18: Net earnings | D18: =D16-D17 -> 564348 | E18: =E16-E17 -> 663169 | F18: =F16-F17 -> 801863 | G18: =G16-G17 -> 1010460 | H18: =H16-H17 -> 1168545 | I18: =I16-I17 -> 1309438
C20: Other comprehensive income (loss)
C21: Items that may be reclassified subsequently to net earnings
C22: Realized gains on financial instruments not subject to basis adjustments | D22: ='Data-Income Statement'!C16 -> -460 | E22: ='Data-Income Statement'!D16 -> 723 | F22: ='Data-Income Statement'!E16 -> 9245 | G22: ='Data-Income Statement'!F16 -> 13841 | H22: ='Data-Income Statement'!G16 -> 0 | I22: ='Data-Income Statement'!H16 -> 0
C23: Reclassification of amortization of net gains on derivative financial instruments not subject to basis adjustments | D23: ='Data-Income Statement'!C17 -> -354 | E23: ='Data-Income Statement'!D17 -> -435 | F23: ='Data-Income Statement'!E17 -> -1019 | G23: ='Data-Income Statement'!F17 -> -3237 | H23: ='Data-Income Statement'!G17 -> -4826 | I23: ='Data-Income Statement'!H17 -> -4735
C24: Foreign currency translation adjustments | D24: ='Data-Income Statement'!C18 -> -8061 | E24: ='Data-Income Statement'!D18 -> 614 | F24: ='Data-Income Statement'!E18 -> 10813 | G24: ='Data-Income Statement'!F18 -> 4004 | H24: ='Data-Income Statement'!G18 -> 76436 | I24: ='Data-Income Statement'!H18 -> -70225
C25: Share of other comprehensive income (loss) of equity-accounted investments | D25: ='Data-Income Statement'!C19 -> -3588 | E25: ='Data-Income Statement'!D19 -> -1217 | F25: ='Data-Income Statement'!E19 -> -6031 | G25: ='Data-Income Statement'!F19 -> 23249 | H25: ='Data-Income Statement'!G19 -> -23480 | I25: ='Data-Income Statement'!H19 -> 33473
C26: Income tax recovery relating to components of OCI that may be reclassified to net earnings | D26: ='Data-Income Statement'!C20 -> 240 | E26: ='Data-Income Statement'!D20 -> 115 | F26: ='Data-Income Statement'!E20 -> -2176 | G26: ='Data-Income Statement'!F20 -> -2807 | H26: ='Data-Income Statement'!G20 -> 1277 | I26: ='Data-Income Statement'!H20 -> 1253
C27: Items that will not be reclassified subsequently to net earnings | D27: ='Data-Income Statement'!C21 -> 0 | E27: ='Data-Income Statement'!D21 -> 0 | F27: ='Data-Income Statement'!E21 -> 0 | G27: ='Data-Income Statement'!F21 -> 0 | H27: ='Data-Income Statement'!G21 -> 0 | I27: ='Data-Income Statement'!H21 -> 0
C28: Unrealized gains (losses) on derivative financial instruments subject to basis adjustments | D28: ='Data-Income Statement'!C22 -> -27750 | E28: ='Data-Income Statement'!D22 -> -294 | F28: ='Data-Income Statement'!E22 -> 38016 | G28: ='Data-Income Statement'!F22 -> 12984 | H28: ='Data-Income Statement'!G22 -> 50582 | I28: ='Data-Income Statement'!H22 -> -48470
C29: Income tax recovery (expense) relating to components of OCI that will not be reclassified to net earnings | D29: ='Data-Income Statement'!C23 -> 7353 | E29: ='Data-Income Statement'!D23 -> -576 | F29: ='Data-Income Statement'!E23 -> -9934 | G29: ='Data-Income Statement'!F23 -> -3152 | H29: ='Data-Income Statement'!G23 -> -13680 | I29: ='Data-Income Statement'!H23 -> 13011
C30: Total other comprehensive income (loss), net of income taxes | D30: =SUM(D22:D29) -> -32620 | E30: =SUM(E22:E29) -> -1070 | F30: =SUM(F22:F29) -> 38914 | G30: =SUM(G22:G29) -> 44882 | H30: =SUM(H22:H29) -> 86309 | I30: =SUM(I22:I29) -> -75693
C31: Total comprehensive income | D31: =D18+D30 -> 531728 | E31: =E18+E30 -> 662099 | F31: =F18+F30 -> 840777 | G31: =G18+G30 -> 1055342 | H31: =H18+H30 -> 1254854 | I31: =I18+I30 -> 1233745
C33: Earnings per common share
C34: Basic net earnings per common share | D34: ='Data-Income Statement'!C27 -> 1.82 | E34: ='Data-Income Statement'!D27 -> 2.19 | F34: ='Data-Income Statement'!E27 -> 2.77 | G34: ='Data-Income Statement'!F27 -> 3.57 | H34: ='Data-Income Statement'!G27 -> 4.18 | I34: ='Data-Income Statement'!H27 -> 4.75
C35: Diluted net earnings per common share | D35: ='Data-Income Statement'!C28 -> 1.81 | E35: ='Data-Income Statement'!D28 -> 2.18 | F35: ='Data-Income Statement'!E28 -> 2.76 | G35: ='Data-Income Statement'!F28 -> 3.56 | H35: ='Data-Income Statement'!G28 -> 4.16 | I35: ='Data-Income Statement'!H28 -> 4.73
C36: Weighted average number of common shares outstanding (thousands) | D36: ='Data-Income Statement'!C29 -> 310738 | E36: ='Data-Income Statement'!D29 -> 302963 | F36: ='Data-Income Statement'!E29 -> 289412 | G36: ='Data-Income Statement'!F29 -> 283074 | H36: ='Data-Income Statement'!G29 -> 279825 | I36: ='Data-Income Statement'!H29 -> 275611
C37: Weighted average number of diluted common shares outstanding (thousands) | D37: ='Data-Income Statement'!C30 -> 312455 | E37: ='Data-Income Statement'!D30 -> 304416 | F37: ='Data-Income Statement'!E30 -> 291005 | G37: ='Data-Income Statement'!F30 -> 284168 | H37: ='Data-Income Statement'!G30 -> 280819 | I37: ='Data-Income Statement'!H30 -> 276684

Sheet Cash Flow
C2: Dollarama Inc.
C3: Consolidated Cash Flow Statement 2026-2021
C4: (Expressed in thousands of Canadian dollars)
C6: Line Item (CAD $ Thousands) | D6: FY2021 | E6: FY2022 | F6: FY2023 | G6: FY2024 | H6: FY2025 | I6: FY2026
C7: ='Data-Cash Flow Statement'!B2 -> Operating activities
C8: ='Data-Cash Flow Statement'!B3 -> Net earnings | D8: ='Data-Cash Flow Statement'!C3 -> 564348 | E8: ='Data-Cash Flow Statement'!D3 -> 663169 | F8: ='Data-Cash Flow Statement'!E3 -> 801863 | G8: ='Data-Cash Flow Statement'!F3 -> 1010460 | H8: ='Data-Cash Flow Statement'!G3 -> 1168545 | I8: ='Data-Cash Flow Statement'!H3 -> 1309438
C10: ='Data-Cash Flow Statement'!B4 -> Adjustments to reconcile net earnings to net cash generated from operating activities:
C11: ='Data-Cash Flow Statement'!B5 -> Depreciation of PP&E, ROU assets and amortization of intangible assets | D11: ='Data-Cash Flow Statement'!C5 -> 269633 | E11: ='Data-Cash Flow Statement'!D5 -> 297960 | F11: ='Data-Cash Flow Statement'!E5 -> 331792 | G11: ='Data-Cash Flow Statement'!F5 -> 365445 | H11: ='Data-Cash Flow Statement'!G5 -> 411151 | I11: ='Data-Cash Flow Statement'!H5 -> 460019
C12: ='Data-Cash Flow Statement'!B6 -> Amortization of debt issue costs | D12: ='Data-Cash Flow Statement'!C6 -> 2673 | E12: ='Data-Cash Flow Statement'!D6 -> 2316 | F12: ='Data-Cash Flow Statement'!E6 -> 0 | G12: ='Data-Cash Flow Statement'!F6 -> 0 | H12: ='Data-Cash Flow Statement'!G6 -> 0 | I12: ='Data-Cash Flow Statement'!H6 -> 0
C13: ='Data-Cash Flow Statement'!B7 -> Amortization of net gains on bond lock and bond forward contracts | D13: ='Data-Cash Flow Statement'!C7 -> -354 | E13: ='Data-Cash Flow Statement'!D7 -> -435 | F13: ='Data-Cash Flow Statement'!E7 -> 0 | G13: ='Data-Cash Flow Statement'!F7 -> 0 | H13: ='Data-Cash Flow Statement'!G7 -> 0 | I13: ='Data-Cash Flow Statement'!H7 -> 0
C14: ='Data-Cash Flow Statement'!B8 -> Share-based compensation | D14: ='Data-Cash Flow Statement'!C8 -> 6240 | E14: ='Data-Cash Flow Statement'!D8 -> 8617 | F14: ='Data-Cash Flow Statement'!E8 -> 14187 | G14: ='Data-Cash Flow Statement'!F8 -> 13102 | H14: ='Data-Cash Flow Statement'!G8 -> 15507 | I14: ='Data-Cash Flow Statement'!H8 -> 16023
C15: ='Data-Cash Flow Statement'!B9 -> Net financing costs | D15: ='Data-Cash Flow Statement'!C9 -> 0 | E15: ='Data-Cash Flow Statement'!D9 -> 0 | F15: ='Data-Cash Flow Statement'!E9 -> 115394 | G15: ='Data-Cash Flow Statement'!F9 -> 144842 | H15: ='Data-Cash Flow Statement'!G9 -> 163782 | I15: ='Data-Cash Flow Statement'!H9 -> 184020
C16: ='Data-Cash Flow Statement'!B10 -> Financing costs on short-term borrowings and long-term debt and realized gains (losses) on financial instruments | D16: ='Data-Cash Flow Statement'!C10 -> -816 | E16: ='Data-Cash Flow Statement'!D10 -> 352 | F16: ='Data-Cash Flow Statement'!E10 -> 0 | G16: ='Data-Cash Flow Statement'!F10 -> 0 | H16: ='Data-Cash Flow Statement'!G10 -> 0 | I16: ='Data-Cash Flow Statement'!H10 -> 0
C17: ='Data-Cash Flow Statement'!B11 -> Deferred income taxes | D17: ='Data-Cash Flow Statement'!C11 -> 15843 | E17: ='Data-Cash Flow Statement'!D11 -> 19529 | F17: ='Data-Cash Flow Statement'!E11 -> -7488 | G17: ='Data-Cash Flow Statement'!F11 -> -10237 | H17: ='Data-Cash Flow Statement'!G11 -> -10618 | I17: ='Data-Cash Flow Statement'!H11 -> -8834
C18: ='Data-Cash Flow Statement'!B12 -> Gain on lease remeasurements | D18: ='Data-Cash Flow Statement'!C12 -> -4822 | E18: ='Data-Cash Flow Statement'!D12 -> -2535 | F18: ='Data-Cash Flow Statement'!E12 -> 0 | G18: ='Data-Cash Flow Statement'!F12 -> 0 | H18: ='Data-Cash Flow Statement'!G12 -> 0 | I18: ='Data-Cash Flow Statement'!H12 -> 0
C19: ='Data-Cash Flow Statement'!B13 -> Unrealized gain from derivative on equity-accounted investments | D19: ='Data-Cash Flow Statement'!C13 -> 0 | E19: ='Data-Cash Flow Statement'!D13 -> 0 | F19: ='Data-Cash Flow Statement'!E13 -> 0 | G19: ='Data-Cash Flow Statement'!F13 -> 0 | H19: ='Data-Cash Flow Statement'!G13 -> 0 | I19: ='Data-Cash Flow Statement'!H13 -> -10348
C20: ='Data-Cash Flow Statement'!B14 -> Share of net earnings of equity-accounted investments | D20: ='Data-Cash Flow Statement'!C14 -> -19654 | E20: ='Data-Cash Flow Statement'!D14 -> -33184 | F20: ='Data-Cash Flow Statement'!E14 -> -45399 | G20: ='Data-Cash Flow Statement'!F14 -> -75293 | H20: ='Data-Cash Flow Statement'!G14 -> -129905 | I20: ='Data-Cash Flow Statement'!H14 -> -191536
C21: ='Data-Cash Flow Statement'!B15 -> Interest received | D21: ='Data-Cash Flow Statement'!C15 -> 0 | E21: ='Data-Cash Flow Statement'!D15 -> 0 | F21: ='Data-Cash Flow Statement'!E15 -> 9218 | G21: ='Data-Cash Flow Statement'!F15 -> 27580 | H21: ='Data-Cash Flow Statement'!G15 -> 29414 | I21: ='Data-Cash Flow Statement'!H15 -> 25562
C22: ='Data-Cash Flow Statement'!B16 -> Other | D22: ='Data-Cash Flow Statement'!C16 -> 0 | E22: ='Data-Cash Flow Statement'!D16 -> 0 | F22: ='Data-Cash Flow Statement'!E16 -> 694 | G22: ='Data-Cash Flow Statement'!F16 -> 2511 | H22: ='Data-Cash Flow Statement'!G16 -> 3015 | I22: ='Data-Cash Flow Statement'!H16 -> 32686
C23: ='Data-Cash Flow Statement'!B17 -> Cash generated from operations before working capital changes | D23: =SUM(D11:D22)+D8 -> 833091 | E23: =SUM(E11:E22)+E8 -> 955789 | F23: =SUM(F11:F22)+F8 -> 1220261 | G23: =SUM(G11:G22)+G8 -> 1478410 | H23: =SUM(H11:H22)+H8 -> 1650891 | I23: =SUM(I11:I22)+I8 -> 1817030
C25: ='Data-Cash Flow Statement'!B18 -> Changes in non-cash working capital components | D25: ='Data-Cash Flow Statement'!C18 -> 55531 | E25: ='Data-Cash Flow Statement'!D18 -> 110094 | F25: ='Data-Cash Flow Statement'!E18 -> -351218 | G25: ='Data-Cash Flow Statement'!F18 -> 52544 | H25: ='Data-Cash Flow Statement'!G18 -> -6752 | I25: ='Data-Cash Flow Statement'!H18 -> -55874
C26: ='Data-Cash Flow Statement'!B19 -> Net cash generated from operating activities | D26: =D23+D25 -> 888622 | E26: =E23+E25 -> 1065883 | F26: =F23+F25 -> 869043 | G26: =G23+G25 -> 1530954 | H26: =H23+H25 -> 1644139 | I26: =I23+I25 -> 1761156
C28: ='Data-Cash Flow Statement'!B20 -> Investing activities
C29: ='Data-Cash Flow Statement'!B21 -> Acquisition of a business, net of cash acquired | D29: ='Data-Cash Flow Statement'!C21 -> 0 | E29: ='Data-Cash Flow Statement'!D21 -> 0 | F29: ='Data-Cash Flow Statement'!E21 -> 0 | G29: ='Data-Cash Flow Statement'!F21 -> 0 | H29: ='Data-Cash Flow Statement'!G21 -> 0 | I29: ='Data-Cash Flow Statement'!H21 -> -181831
C30: ='Data-Cash Flow Statement'!B22 -> Addition to equity-accounted investments | D30: ='Data-Cash Flow Statement'!C22 -> -97281 | E30: ='Data-Cash Flow Statement'!D22 -> 0 | F30: ='Data-Cash Flow Statement'!E22 -> 0 | G30: ='Data-Cash Flow Statement'!F22 -> 0 | H30: ='Data-Cash Flow Statement'!G22 -> -5402 | I30: ='Data-Cash Flow Statement'!H22 -> -49960
C31: ='Data-Cash Flow Statement'!B23 -> Distributions from equity-accounted investments | D31: ='Data-Cash Flow Statement'!C23 -> 0 | E31: ='Data-Cash Flow Statement'!D23 -> 0 | F31: ='Data-Cash Flow Statement'!E23 -> 0 | G31: ='Data-Cash Flow Statement'!F23 -> 26960 | H31: ='Data-Cash Flow Statement'!G23 -> 27397 | I31: ='Data-Cash Flow Statement'!H23 -> 106554
C32: ='Data-Cash Flow Statement'!B24 -> Additions to property, plant and equipment | D32: ='Data-Cash Flow Statement'!C24 -> -140040 | E32: ='Data-Cash Flow Statement'!D24 -> -136772 | F32: ='Data-Cash Flow Statement'!E24 -> -134049 | G32: ='Data-Cash Flow Statement'!F24 -> -252673 | H32: ='Data-Cash Flow Statement'!G24 -> -212828 | I32: ='Data-Cash Flow Statement'!H24 -> -248747
C33: ='Data-Cash Flow Statement'!B25 -> Additions to intangible assets | D33: ='Data-Cash Flow Statement'!C25 -> -27797 | E33: ='Data-Cash Flow Statement'!D25 -> -22740 | F33: ='Data-Cash Flow Statement'!E25 -> -22778 | G33: ='Data-Cash Flow Statement'!F25 -> -26091 | H33: ='Data-Cash Flow Statement'!G25 -> -30622 | I33: ='Data-Cash Flow Statement'!H25 -> -24034
C34: ='Data-Cash Flow Statement'!B26 -> Initial direct costs on right-of-use assets | D34: ='Data-Cash Flow Statement'!C26 -> 0 | E34: ='Data-Cash Flow Statement'!D26 -> 0 | F34: ='Data-Cash Flow Statement'!E26 -> 0 | G34: ='Data-Cash Flow Statement'!F26 -> 0 | H34: ='Data-Cash Flow Statement'!G26 -> 0 | I34: ='Data-Cash Flow Statement'!H26 -> -6554
C35: ='Data-Cash Flow Statement'!B27 -> Proceeds from disposal of property, plant and equipment | D35: ='Data-Cash Flow Statement'!C27 -> 593 | E35: ='Data-Cash Flow Statement'!D27 -> 839 | F35: ='Data-Cash Flow Statement'!E27 -> 278 | G35: ='Data-Cash Flow Statement'!F27 -> 938 | H35: ='Data-Cash Flow Statement'!G27 -> 736 | I35: ='Data-Cash Flow Statement'!H27 -> 1077
C36: ='Data-Cash Flow Statement'!B28 -> Net cash used in investing activities | D36: ='Data-Cash Flow Statement'!C28 -> -264525 | E36: ='Data-Cash Flow Statement'!D28 -> -158673 | F36: ='Data-Cash Flow Statement'!E28 -> -156549 | G36: ='Data-Cash Flow Statement'!F28 -> -250866 | H36: ='Data-Cash Flow Statement'!G28 -> -220719 | I36: ='Data-Cash Flow Statement'!H28 -> -403495
C38: ='Data-Cash Flow Statement'!B29 -> Financing activities
C39: ='Data-Cash Flow Statement'!B30 -> Proceeds from long-term debt issued | D39: ='Data-Cash Flow Statement'!C30 -> 0 | E39: ='Data-Cash Flow Statement'!D30 -> 0 | F39: ='Data-Cash Flow Statement'!E30 -> 700000 | G39: ='Data-Cash Flow Statement'!F30 -> 500000 | H39: ='Data-Cash Flow Statement'!G30 -> 0 | I39: ='Data-Cash Flow Statement'!H30 -> 600000
C40: ='Data-Cash Flow Statement'!B31 -> Proceeds from long-term debt issued (1.505% Fixed Rate Notes) | D40: ='Data-Cash Flow Statement'!C31 -> 300000 | E40: ='Data-Cash Flow Statement'!D31 -> 0 | F40: ='Data-Cash Flow Statement'!E31 -> 0 | G40: ='Data-Cash Flow Statement'!F31 -> 0 | H40: ='Data-Cash Flow Statement'!G31 -> 0 | I40: ='Data-Cash Flow Statement'!H31 -> 0
C41: ='Data-Cash Flow Statement'!B32 -> Proceeds from long-term debt issued (1.871% Fixed Rate Notes) | D41: ='Data-Cash Flow Statement'!C32 -> 0 | E41: ='Data-Cash Flow Statement'!D32 -> 375000 | F41: ='Data-Cash Flow Statement'!E32 -> 0 | G41: ='Data-Cash Flow Statement'!F32 -> 0 | H41: ='Data-Cash Flow Statement'!G32 -> 0 | I41: ='Data-Cash Flow Statement'!H32 -> 0
C42: ='Data-Cash Flow Statement'!B33 -> Proceeds from long-term debt issued (2.443% Fixed Rate Notes) | D42: ='Data-Cash Flow Statement'!C33 -> 0 | E42: ='Data-Cash Flow Statement'!D33 -> 375000 | F42: ='Data-Cash Flow Statement'!E33 -> 0 | G42: ='Data-Cash Flow Statement'!F33 -> 0 | H42: ='Data-Cash Flow Statement'!G33 -> 0 | I42: ='Data-Cash Flow Statement'!H33 -> 0
C43: ='Data-Cash Flow Statement'!B34 -> Repayment of long-term debt | D43: ='Data-Cash Flow Statement'!C34 -> 0 | E43: ='Data-Cash Flow Statement'!D34 -> 0 | F43: ='Data-Cash Flow Statement'!E34 -> -250000 | G43: ='Data-Cash Flow Statement'!F34 -> -500000 | H43: ='Data-Cash Flow Statement'!G34 -> 0 | I43: ='Data-Cash Flow Statement'!H34 -> -250000
C44: ='Data-Cash Flow Statement'!B35 -> Repayment of the Series 2 Floating Rate Notes or the Series 3 Floating Rate Notes (as applicable) | D44: ='Data-Cash Flow Statement'!C35 -> -300000 | E44: ='Data-Cash Flow Statement'!D35 -> -300000 | F44: ='Data-Cash Flow Statement'!E35 -> 0 | G44: ='Data-Cash Flow Statement'!F35 -> 0 | H44: ='Data-Cash Flow Statement'!G35 -> 0 | I44: ='Data-Cash Flow Statement'!H35 -> 0
C45: ='Data-Cash Flow Statement'!B36 -> Repayment of the 2.337% Fixed Rate Notes | D45: ='Data-Cash Flow Statement'!C36 -> 0 | E45: ='Data-Cash Flow Statement'!D36 -> -525000 | F45: ='Data-Cash Flow Statement'!E36 -> 0 | G45: ='Data-Cash Flow Statement'!F36 -> 0 | H45: ='Data-Cash Flow Statement'!G36 -> 0 | I45: ='Data-Cash Flow Statement'!H36 -> 0
C46: ='Data-Cash Flow Statement'!B37 -> Repayment of short-term borrowings | D46: ='Data-Cash Flow Statement'!C37 -> 0 | E46: ='Data-Cash Flow Statement'!D37 -> 0 | F46: ='Data-Cash Flow Statement'!E37 -> -88385 | G46: ='Data-Cash Flow Statement'!F37 -> 0 | H46: ='Data-Cash Flow Statement'!G37 -> 0 | I46: ='Data-Cash Flow Statement'!H37 -> 0
C47: ='Data-Cash Flow Statement'!B38 -> Net proceeds from short-term borrowings | D47: ='Data-Cash Flow Statement'!C38 -> 0 | E47: ='Data-Cash Flow Statement'!D38 -> 88381 | F47: ='Data-Cash Flow Statement'!E38 -> 0 | G47: ='Data-Cash Flow Statement'!F38 -> 0 | H47: ='Data-Cash Flow Statement'!G38 -> 0 | I47: ='Data-Cash Flow Statement'!H38 -> 0
C48: ='Data-Cash Flow Statement'!B39 -> Interest paid on long-term debt, long-term financing arrangements and short-term borrowings | D48: ='Data-Cash Flow Statement'!C39 -> 0 | E48: ='Data-Cash Flow Statement'!D39 -> 0 | F48: ='Data-Cash Flow Statement'!E39 -> -64180 | G48: ='Data-Cash Flow Statement'!F39 -> -100811 | H48: ='Data-Cash Flow Statement'!G39 -> -108490 | I48: ='Data-Cash Flow Statement'!H39 -> -114516
C49: ='Data-Cash Flow Statement'!B40 -> Payment of debt issue costs | D49: ='Data-Cash Flow Statement'!C40 -> -2200 | E49: ='Data-Cash Flow Statement'!D40 -> -4174 | F49: ='Data-Cash Flow Statement'!E40 -> -3847 | G49: ='Data-Cash Flow Statement'!F40 -> -2896 | H49: ='Data-Cash Flow Statement'!G40 -> -480 | I49: ='Data-Cash Flow Statement'!H40 -> -3584
C50: ='Data-Cash Flow Statement'!B41 -> Proceeds on bond forward settlement | D50: ='Data-Cash Flow Statement'!C41 -> 0 | E50: ='Data-Cash Flow Statement'!D41 -> 0 | F50: ='Data-Cash Flow Statement'!E41 -> 10416 | G50: ='Data-Cash Flow Statement'!F41 -> 13841 | H50: ='Data-Cash Flow Statement'!G41 -> 0 | I50: ='Data-Cash Flow Statement'!H41 -> 0
... C57: ='Data-Cash Flow Statement'!B48 -> Net cash used in financing activities | D57: ='Data-Cash Flow Statement'!C48 -> -275417 | E57: ='Data-Cash Flow Statement'!D48 -> -1275296 | F57: ='Data-Cash Flow Statement'!E48 -> -682291 | G57: ='Data-Cash Flow Statement'!F48 -> -1067434 | H57: ='Data-Cash Flow Statement'!G48 -> -1614650 | I57: ='Data-Cash Flow Statement'!H48 -> -1148777
C59: ='Data-Cash Flow Statement'!B49 -> Change in cash and cash equivalents | D59: =D61-D60 -> 348680 | E59: =E61-E60 -> -368086 | F59: =F61-F60 -> 30203 | G59: =G61-G60 -> 212654 | H59: =H61-H60 -> -191230 | I59: =I61-I60 -> 208884
C60: ='Data-Cash Flow Statement'!B50 -> Cash and cash equivalents – beginning of year | D60: ='Data-Cash Flow Statement'!C50 -> 90464 | E60: ='Data-Cash Flow Statement'!D50 -> 439144 | F60: ='Data-Cash Flow Statement'!E50 -> 71058 | G60: ='Data-Cash Flow Statement'!F50 -> 101261 | H60: ='Data-Cash Flow Statement'!G50 -> 313915 | I60: ='Data-Cash Flow Statement'!H50 -> 122685
C61: ='Data-Cash Flow Statement'!B51 -> Cash and cash equivalents – end of year | D61: ='Data-Cash Flow Statement'!C51 -> 439144 | E61: ='Data-Cash Flow Statement'!D51 -> 71058 | F61: ='Data-Cash Flow Statement'!E51 -> 101261 | G61: ='Data-Cash Flow Statement'!F51 -> 313915 | H61: ='Data-Cash Flow Statement'!G51 -> 122685 | I61: ='Data-Cash Flow Statement'!H51 -> 331569
C63: ='Data-Cash Flow Statement'!B52 -> Supplemental information:
C64: ='Data-Cash Flow Statement'!B53 -> Interest paid on lease liabilities | D64: ='Data-Cash Flow Statement'!C53 -> 0 | E64: ='Data-Cash Flow Statement'!D53 -> 0 | F64: ='Data-Cash Flow Statement'!E53 -> 52307 | G64: ='Data-Cash Flow Statement'!F53 -> 66587 | H64: ='Data-Cash Flow Statement'!G53 -> 86730 | I64: ='Data-Cash Flow Statement'!H53 -> 99087

Sheet Data-Cash Flow Statement
A1: Index | B1: LineItem | C1: FY2021 | D1: FY2022 | E1: FY2023 | F1: FY2024 | G1: FY2025 | H1: FY2026
A2: 0 | B2: Operating activities
A3: 1 | B3: Net earnings | C3: 564348 | D3: 663169 | E3: 801863 | F3: 1010460 | G3: 1168545 | H3: 1309438
A4: 2 | B4: Adjustments to reconcile net earnings to net cash generated from operating activities:
A5: 3 | B5: Depreciation of PP&E, ROU assets and amortization of intangible assets | C5: 269633 | D5: 297960 | E5: 331792 | F5: 365445 | G5: 411151 | H5: 460019
A6: 4 | B6: Amortization of debt issue costs | C6: 2673 | D6: 2316
A7: 5 | B7: Amortization of net gains on bond lock and bond forward contracts | C7: -354 | D7: -435
A8: 6 | B8: Share-based compensation | C8: 6240 | D8: 8617 | E8: 14187 | F8: 13102 | G8: 15507 | H8: 16023
A9: 7 | B9: Net financing costs | E9: 115394 | F9: 144842 | G9: 163782 | H9: 184020
A10: 8 | B10: Financing costs on short-term borrowings and long-term debt and realized gains (losses) on financial instruments | C10: -816 | D10: 352
A11: 9 | B11: Deferred income taxes | C11: 15843 | D11: 19529 | E11: -7488 | F11: -10237 | G11: -10618 | H11: -8834
A12: 10 | B12: Gain on lease remeasurements | C12: -4822 | D12: -2535
A13: 11 | B13: Unrealized gain from derivative on equity-accounted investments | G13: 0 | H13: -10348
A14: 12 | B14: Share of net earnings of equity-accounted investments | C14: -19654 | D14: -33184 | E14: -45399 | F14: -75293 | G14: -129905 | H14: -191536
A15: 13 | B15: Interest received | E15: 9218 | F15: 27580 | G15: 29414 | H15: 25562
A16: 14 | B16: Other | E16: 694 | F16: 2511 | G16: 3015 | H16: 32686
A17: 15 | B17: Cash generated from operations before working capital changes | C17: 833091 | D17: 955789 | E17: 1220261 | F17: 1478410 | G17: 1650891 | H17: 1817030
A18: 16 | B18: Changes in non-cash working capital components | C18: 55531 | D18: 110094 | E18: -351218 | F18: 52544 | G18: -6752 | H18: -55874
A19: 17 | B19: Net cash generated from operating activities | C19: 888622 | D19: 1065883 | E19: 869043 | F19: 1530954 | G19: 1644139 | H19: 1761156
A20: 18 | B20: Investing activities
A21: 19 | B21: Acquisition of a business, net of cash acquired | G21: 0 | H21: -181831
A22: 20 | B22: Addition to equity-accounted investments | C22: -97281 | D22: 0 | G22: -5402 | H22: -49960
A23: 21 | B23: Distributions from equity-accounted investments | E23: 0 | F23: 26960 | G23: 27397 | H23: 106554
A24: 22 | B24: Additions to property, plant and equipment | C24: -140040 | D24: -136772 | E24: -134049 | F24: -252673 | G24: -212828 | H24: -248747
A25: 23 | B25: Additions to intangible assets | C25: -27797 | D25: -22740 | E25: -22778 | F25: -26091 | G25: -30622 | H25: -24034
A26: 24 | B26: Initial direct costs on right-of-use assets | G26: 0 | H26: -6554
A27: 25 | B27: Proceeds from disposal of property, plant and equipment | C27: 593 | D27: 839 | E27: 278 | F27: 938 | G27: 736 | H27: 1077
A28: 26 | B28: Net cash used in investing activities | C28: -264525 | D28: -158673 | E28: -156549 | F28: -250866 | G28: -220719 | H28: -403495
A29: 27 | B29: Financing activities
A30: 28 | B30: Proceeds from long-term debt issued | E30: 700000 | F30: 500000 | G30: 0 | H30: 600000
A31: 29 | B31: Proceeds from long-term debt issued (1.505% Fixed Rate Notes) | C31: 300000 | D31: 0
A32: 30 | B32: Proceeds from long-term debt issued (1.871% Fixed Rate Notes) | C32: 0 | D32: 375000
A33: 31 | B33: Proceeds from long-term debt issued (2.443% Fixed Rate Notes) | C33: 0 | D33: 375000
A34: 32 | B34: Repayment of long-term debt | E34: -250000 | F34: -500000 | G34: 0 | H34: -250000
A35: 33 | B35: Repayment of the Series 2 Floating Rate Notes or the Series 3 Floating Rate Notes (as applicable) | C35: -300000 | D35: -300000
A36: 34 | B36: Repayment of the 2.337% Fixed Rate Notes | C36: 0 | D36: -525000
A37: 35 | B37: Repayment of short-term borrowings | E37: -88385 | F37: 0
A38: 36 | B38: Net proceeds from short-term borrowings | C38: 0 | D38: 88381
A39: 37 | B39: Interest paid on long-term debt, long-term financing arrangements and short-term borrowings | E39: -64180 | F39: -100811 | G39: -108490 | H39: -114516
A40: 38 | B40: Payment of debt issue costs | C40: -2200 | D40: -4174 | E40: -3847 | F40: -2896 | G40: -480 | H40: -3584
A41: 39 | B41: Proceeds on bond forward settlement | E41: 10416 | F41: 13841
A42: 40 | B42: Net payment of lease liabilities | C42: -163804 | D42: -183285 | E42: -253566 | F42: -284836 | G42: -317829 | H42: -390333
A43: 41 | B43: Issuance of common shares | C43: 32399 | D43: 19164 | E43: 19242 | F43: 39268 | G43: 19772 | H43: 8840
A44: 42 | B44: Dividends paid | C44: -54770 | D44: -60464 | E44: -62975 | F44: -76131 | G44: -97244 | H44: -113196
A45: 43 | B45: Repurchase and cancellation of common shares | C45: -87042 | D45: -1059918 | E45: -688996 | F45: -655869 | G45: -1070712 | H45: -854414
A46: 44 | B46: Repurchase of treasury shares, net of dividends | G46: -20000 | H46: -9970
A47: 45 | B47: Performance share units settlement | G47: -19667 | H47: -21604
A48: 46 | B48: Net cash used in financing activities | C48: -275417 | D48: -1275296 | E48: -682291 | F48: -1067434 | G48: -1614650 | H48: -1148777
A49: 47 | B49: Change in cash and cash equivalents | C49: 348680 | D49: -368086 | E49: 30203 | F49: 212654 | G49: -191230 | H49: 208884
A50: 48 | B50: Cash and cash equivalents – beginning of year | C50: 90464 | D50: 439144 | E50: 71058 | F50: 101261 | G50: 313915 | H50: 122685
A51: 49 | B51: Cash and cash equivalents – end of year | C51: 439144 | D51: 71058 | E51: 101261 | F51: 313915 | G51: 122685 | H51: 331569
A52: 50 | B52: Supplemental information:
A53: 51 | B53: Interest paid on lease liabilities | C53: 0 | D53: 0 | E53: 52307 | F53: 66587 | G53: 86730 | H53: 99087

Sheet Data-Income Statement
A1: Index | B1: LineItem | C1: FY2021 | D1: FY2022 | E1: FY2023 | F1: FY2024 | G1: FY2025 | H1: FY2026
A2: 0 | B2: Sales | G2: 6413145 | H2: 7255754
A3: 1 | B3: Cost of sales | G3: 3519399 | H3: 3987089
A4: 2 | B4: Gross profit | G4: 2893746 | H4: 3268665
A5: 3 | B5: General, administrative and store operating expenses | G5: 930168 | H5: 1093289
A6: 4 | B6: Depreciation and amortization | G6: 382805 | H6: 429053
A7: 5 | B7: Share of net earnings of equity-accounted investments | G7: -129905 | H7: -191536
A8: 6 | B8: Operating income | G8: 1710678 | H8: 1937859
A9: 7 | B9: Unrealized gain from derivative on equity-accounted investments | G9: 0 | H9: -10348
A10: 8 | B10: Net financing costs | G10: 163782 | H10: 184020
A11: 9 | B11: Earnings before income taxes | G11: 1546896 | H11: 1764187
A12: 10 | B12: Income taxes | G12: 378351 | H12: 454749
A13: 11 | B13: Net earnings | G13: 1168545 | H13: 1309438
A14: 12 | B14: Other comprehensive income (loss)
A15: 13 | B15: Items that may be reclassified subsequently to net earnings
A16: 14 | B16: Realized gains on financial instruments not subject to basis adjustments | C16: -460 | D16: 723 | E16: 9245 | F16: 13841
A17: 15 | B17: Reclassification of amortization of net gains on derivative financial instruments not subject to basis adjustments | C17: -354 | D17: -435 | E17: -1019 | F17: -3237 | G17: -4826 | H17: -4735
A18: 16 | B18: Foreign currency translation adjustments | C18: -8061 | D18: 614 | E18: 10813 | F18: 4004 | G18: 76436 | H18: -70225
A19: 17 | B19: Share of other comprehensive income (loss) of equity-accounted investments | C19: -3588 | D19: -1217 | E19: -6031 | F19: 23249 | G19: -23480 | H19: 33473
A20: 18 | B20: Income tax recovery relating to components of OCI that may be reclassified to net earnings | C20: 240 | D20: 115 | E20: -2176 | F20: -2807 | G20: 1277 | H20: 1253
A21: 19 | B21: Items that will not be reclassified subsequently to net earnings | C21: 0 | D21: 0 | E21: 0 | F21: 0 | G21: 0 | H21: 0
A22: 20 | B22: Unrealized gains (losses) on derivative financial instruments subject to basis adjustments | C22: -27750 | D22: -294 | E22: 38016 | F22: 12984 | G22: 50582 | H22: -48470
A23: 21 | B23: Income tax recovery (expense) relating to components of OCI that will not be reclassified to net earnings | C23: 7353 | D23: -576 | E23: -9934 | F23: -3152 | G23: -13680 | H23: 13011
A24: 22 | B24: Total other comprehensive income (loss), net of income taxes | C24: -32620 | D24: -1070 | E24: 38914 | F24: 44882 | G24: 86309 | H24: -75693
A25: 23 | B25: Total comprehensive income | C25: 531728 | D25: 662099 | E25: 840777 | F25: 1055342 | G25: 1254854 | H25: 1233745
A26: 24 | B26: Earnings per common share
A27: 25 | B27: Basic net earnings per common share | C27: 1.82 | D27: 2.19 | E27: 2.77 | F27: 3.57 | G27: 4.18 | H27: 4.75
A28: 26 | B28: Diluted net earnings per common share | C28: 1.81 | D28: 2.18 | E28: 2.76 | F28: 3.56 | G28: 4.16 | H28: 4.73
A29: 27 | B29: Weighted average number of common shares outstanding (thousands) | C29: 310738 | D29: 302963 | E29: 289412 | F29: 283074 | G29: 279825 | H29: 275611
A30: 28 | B30: Weighted average number of diluted common shares outstanding (thousands) | C30: 312455 | D30: 304416 | E30: 291005 | F30: 284168 | G30: 280819 | H30: 276684
A31: 29 | B31: Sales | C31: 4026259 | D31: 4330761 | E31: 5052741 | F31: 5867348
A32: 30 | B32: Cost of sales | C32: 2261248 | D32: 2428536 | E32: 2854535 | F32: 3253907
A33: 31 | B33: Gross profit | C33: 1765011 | D33: 1902225 | E33: 2198206 | F33: 2613441
A34: 32 | B34: General, administrative and store operating expenses | C34: 654032 | D34: 652832 | E34: 720312 | F34: 844871
A35: 33 | B35: Depreciation and amortization | C35: 269633 | D35: 297960 | E35: 331792 | F35: 348142
A36: 34 | B36: Share of net earnings of equity-accounted investments | C36: -19654 | D36: -33184 | E36: -45399 | F36: -75293
A37: 35 | B37: Operating income | C37: 861000 | D37: 984617 | E37: 1191501 | F37: 1495721
A38: 36 | B38: Net financing costs | C38: 95646 | D38: 91216 | E38: 115394 | F38: 144842
A39: 37 | B39: Earnings before income taxes | C39: 765354 | D39: 893401 | E39: 1076107 | F39: 1350879
A40: 38 | B40: Income taxes | C40: 201006 | D40: 230232 | E40: 274244 | F40: 340419
A41: 39 | B41: Net earnings | C41: 564348 | D41: 663169 | E41: 801863 | F41: 1010460

Sheet FP-2026_2022
A1: Index | B1: LineItem | C1: FY2021 | D1: FY2022 | E1: FY2023 | F1: FY2024 | G1: FY2025 | H1: FY2026
A2: 0 | B2: Assets
A3: 1 | B3: Current assets
A4: 2 | B4: Cash and cash equivalents | C4: 439144 | D4: 71058 | E4: 101261 | F4: 313915 | G4: 122685 | H4: 331569
A5: 3 | B5: Accounts receivable | C5: 20546 | D5: 26260 | E5: 56290 | F5: 32474 | G5: 46638 | H5: 38500
A6: 4 | B6: Income taxes receivable | G6: 0 | H6: 559
A7: 5 | B7: Distributions receivable from equity-accounted investments | E7: 0 | F7: 26906 | G7: 54620 | H7: 0
A8: 6 | B8: Prepaid expenses | C8: 9549 | D8: 13135 | E8: 23462 | F8: 13668 | G8: 13911 | H8: 38452
A9: 7 | B9: Inventories | C9: 630655 | D9: 590927 | E9: 957172 | F9: 916812 | G9: 921095 | H9: 1103175
A10: 8 | B10: Derivative financial instruments | C10: 468 | D10: 15987 | E10: 18762 | F10: 5318 | G10: 42331 | H10: 9734
A11: 9 | B11: Total current assets | C11: 1100362 | D11: 717367 | E11: 1156947 | F11: 1309093 | G11: 1201280 | H11: 1521989
A12: 10 | B12: Non-current assets
A13: 11 | B13: Right-of-use assets | C13: 1344639 | D13: 1480255 | E13: 1699755 | F13: 1788550 | G13: 2109445 | H13: 2397209
A14: 12 | B14: Property, plant and equipment | C14: 709469 | D14: 761876 | E14: 802750 | F14: 950994 | G14: 1046390 | H14: 1258499
A15: 13 | B15: Intangible assets | C15: 161791 | D15: 164066 | E15: 164654 | F15: 167835 | G15: 180689 | H15: 178281
A16: 14 | B16: Derivative financial instruments | C16: 314 | D16: 290
A17: 15 | B17: Goodwill | C17: 727782 | D17: 727782 | E17: 727782 | F17: 727782 | G17: 727782 | H17: 801709
A18: 16 | B18: Equity-accounted investments | C18: 179389 | D18: 211926 | E18: 267768 | F18: 319353 | G18: 1131650 | H18: 1285105
A19: 17 | B19: Derivative on equity-accounted investments | G19: 85356 | H19: 89846
A20: 18 | B20: Deferred income taxes | G20: 0 | H20: 25714
A21: 19 | B21: Total assets | C21: 4223746 | D21: 4063562 | E21: 4819656 | F21: 5263607 | G21: 6482592 | H21: 7558352
A22: 20 | B22: Liabilities and shareholders' equity
A23: 21 | B23: Current liabilities
A24: 22 | B24: Accounts payable and accrued liabilities | C24: 253072 | D24: 283125 | E24: 336862 | F24: 334357 | G24: 354900 | H24: 461766
A25: 23 | B25: Short-term borrowings | C25: 0 | D25: 89386
A26: 24 | B26: Dividend payable | C26: 14583 | D26: 14891 | E26: 15828 | F26: 19827 | G26: 25558 | H26: 28941
A27: 25 | B27: Derivative financial instruments | C27: 25821 | D27: 3435 | E27: 8490 | F27: 3681 | G27: 0 | H27: 17145
A28: 26 | B28: Income taxes payable | C28: 12975 | D28: 62516 | E28: 72572 | F28: 63998 | G28: 81372 | H28: 64309
A29: 27 | B29: Current portion of long-term debt | C29: 832821 | D29: 257674 | E29: 510315 | F29: 21460 | G29: 273771 | H29: 398275
A30: 28 | B30: Current portion of lease liabilities | C30: 181893 | D30: 200864 | E30: 218807 | F30: 234523 | G30: 278705 | H30: 377743
A31: 29 | B31: Total current liabilities | C31: 1321165 | D31: 911891 | E31: 1162874 | F31: 677846 | G31: 1014306 | H31: 1348179
A32: 30 | B32: Non-current liabilities
A33: 31 | B33: Non-current provisions and other liabilities | G33: 0 | H33: 31982
A34: 32 | B34: Non-current portion of long-term debt | C34: 1044079 | D34: 1539240 | E34: 1741588 | F34: 2242934 | G34: 2008908 | H34: 2226846
A35: 33 | B35: Non-current portion of lease liabilities | C35: 1401769 | D35: 1526564 | E35: 1741936 | F35: 1834706 | G35: 2148272 | H35: 2392730
A36: 34 | B36: Deferred income taxes | C36: 121879 | D36: 151901 | E36: 144848 | F36: 127273 | G36: 122848 | H36: 102727
A37: 35 | B37: Total liabilities | C37: 3888892 | D37: 4129596 | E37: 4791246 | F37: 4882759 | G37: 5294334 | H37: 6102464
A38: 36 | B38: Shareholders' equity
A39: 37 | B39: Share capital | C39: 485487 | D39: 479446 | E39: 488074 | F39: 523125 | G39: 1275702 | H39: 1266750
A40: 38 | B40: Treasury shares | G40: -20000 | H40: -29970
A41: 39 | B41: Contributed surplus | C41: 28527 | D41: 32924 | E41: 42678 | F41: 49539 | G41: 51718 | H41: 57572
A42: 40 | B42: Retained earnings (Deficit) | C42: -149983 | D42: -578079 | E42: -514078 | F42: -226547 | G42: -225301 | H42: 128858
A43: 41 | B43: Accumulated other comprehensive income | C43: -29177 | D43: -325 | E43: 11736 | F43: 34731 | G43: 106139 | H43: 32678
A44: 42 | B44: Total shareholders' equity | C44: 334854 | D44: -66034 | E44: 28410 | F44: 380848 | G44: 1188258 | H44: 1455888
A45: 43 | B45: Total liabilities and shareholders' equity | C45: 4223746 | D45: 4063562 | E45: 4819656 | F45: 5263607 | G45: 6482592 | H45: 7558352
